{
  "presetName": "Low Effort Nihils (Magic)",
  "presetNotes": "",
  "equipmentSlots": [
    {
      "image": "https://i.imgur.com/xNXHeIN.png",
      "wikiLink": "https://runescape.wiki/w/Cryptbloom_helm",
      "name": "Cryptbloom helm",
      "breakdownNotes": "",
      "label": "cryptbloomhelm"
    },
    {
      "image": "https://i.imgur.com/jcfkzGn.png",
      "wikiLink": "https://runescape.wiki/w/Igneous_Kal-Zuk",
      "name": "Igneous Kal-Zuk",
      "breakdownNotes": "",
      "label": "kalzuk"
    },
    {
      "image": "https://i.imgur.com/4KgPcpm.png",
      "wikiLink": "https://runescape.wiki/w/Grace_of_the_elves",
      "name": "Grace of the elves",
      "breakdownNotes": "With Porter charges for looting Nihil ingredients",
      "label": "gote"
    },
    {
      "image": "https://i.imgur.com/ysTivBO.png",
      "wikiLink": "https://runescape.wiki/w/Noxious_staff",
      "name": "Noxious staff",
      "breakdownNotes": "T80+ staff for casting <img class=\"disc-emoji\" src=\"https://cdn.discordapp.com/emojis/537338981747261446.png?v=1\" />",
      "label": "noxstaff"
    },
    {
      "image": "https://i.imgur.com/Io6oIdr.png",
      "wikiLink": "https://runescape.wiki/w/Ganodermic_poncho",
      "name": "Ganodermic poncho",
      "breakdownNotes": "",
      "label": "ganobody"
    },
    {
      "image": "",
      "name": "",
      "breakdownNotes": "",
      "label": ""
    },
    {
      "image": "https://i.imgur.com/D3cx9PR.png",
      "wikiLink": "https://runescape.wiki/w/Ganodermic_leggings",
      "name": "Ganodermic leggings",
      "breakdownNotes": "",
      "label": "ganolegs"
    },
    {
      "image": "https://i.imgur.com/LutTgCH.png",
      "wikiLink": "https://runescape.wiki/w/Cinderbane_gloves",
      "name": "Cinderbane gloves",
      "breakdownNotes": "",
      "label": "cinder"
    },
    {
      "image": "https://i.imgur.com/1MkR1qn.png",
      "wikiLink": "https://runescape.wiki/w/Cryptbloom_boots",
      "name": "Cryptbloom boots",
      "breakdownNotes": "",
      "label": "cryptbloomboots"
    },
    {
      "image": "https://i.imgur.com/gpuvlcU.png",
      "wikiLink": "https://runescape.wiki/w/Sixth-Age_circuit",
      "name": "Sixth-Age circuit",
      "breakdownNotes": "",
      "label": "sixthagecircuit"
    },
    {
      "image": "https://i.imgur.com/yrnlR2T.png",
      "wikiLink": "https://runescape.wiki/w/Grasping_rune_pouch_(pink)",
      "name": "Grasping rune pouch (pink)",
      "breakdownNotes": "Death | Earth | Law | Cosmic <span>- Runes for </span><img class=\"disc-emoji\" src=\"https://cdn.discordapp.com/emojis/537338981747261446.png?v=1\" /><span> </span><img class=\"disc-emoji\" src=\"https://cdn.discordapp.com/emojis/856635090453135382.png?v=1\" />",
      "label": "graspingpouchpink"
    },
    {
      "image": "https://i.imgur.com/G4FM1Cz.png",
      "wikiLink": "https://runescape.wiki/w/Penance_aura",
      "name": "Penance aura",
      "breakdownNotes": "",
      "label": "penance"
    },
    {
      "image": "https://i.imgur.com/zd3mKfH.png",
      "wikiLink": "https://runescape.wiki/w/Scripture_of_Wen",
      "name": "Scripture of Wen",
      "breakdownNotes": "",
      "label": "scriptureofwen"
    }
  ],
  "inventorySlots": [
    {
      "image": "https://i.imgur.com/9GP63eS.png",
      "wikiLink": "https://runescape.wiki/w/Elder_overload_salve#(6)",
      "name": "Elder overload salve (6)",
      "breakdownNotes": "",
      "label": "salve",
      "selected": false
    },
    {
      "image": "https://i.imgur.com/CR06fbn.png",
      "wikiLink": "https://runescape.wiki/w/Weapon_poison+++#(4)",
      "name": "Weapon poison+++ (4)",
      "breakdownNotes": "",
      "label": "poison4",
      "selected": false
    },
    {
      "image": "",
      "name": "",
      "breakdownNotes": "",
      "label": "",
      "selected": false
    },
    {
      "image": "",
      "name": "",
      "breakdownNotes": "",
      "label": "",
      "selected": false
    },
    {
      "image": "",
      "name": "",
      "breakdownNotes": "",
      "label": "",
      "selected": false
    },
    {
      "image": "",
      "name": "",
      "breakdownNotes": "",
      "label": "",
      "selected": false
    },
    {
      "image": "",
      "name": "",
      "breakdownNotes": "",
      "label": "",
      "selected": false
    },
    {
      "image": "https://i.imgur.com/nC5xTAR.png",
      "wikiLink": "https://runescape.wiki/w/Enhanced_excalibur",
      "name": "Enhanced excalibur",
      "breakdownNotes": "",
      "label": "excal",
      "selected": false
    },
    {
      "image": "https://i.imgur.com/pjHPdhj.png",
      "wikiLink": "https://runescape.wiki/w/Spring_cleaner_9001",
      "name": "Spring cleaner 9001",
      "breakdownNotes": "",
      "label": "springcleaner",
      "selected": false
    },
    {
      "image": "",
      "name": "",
      "breakdownNotes": "",
      "label": "",
      "selected": false
    },
    {
      "image": "",
      "name": "",
      "breakdownNotes": "",
      "label": "",
      "selected": false
    },
    {
      "image": "",
      "name": "",
      "breakdownNotes": "",
      "label": "",
      "selected": false
    },
    {
      "image": "",
      "name": "",
      "breakdownNotes": "",
      "label": "",
      "selected": false
    },
    {
      "image": "https://i.imgur.com/kJ17hH6.png",
      "wikiLink": "https://runescape.wiki/w/Smoke_nihil_pouch",
      "name": "Smoke nihil pouch",
      "breakdownNotes": "",
      "label": "smokenihil",
      "selected": false
    },
    {
      "image": "https://i.imgur.com/UURvGNW.png",
      "wikiLink": "https://runescape.wiki/w/Ancient_elven_ritual_shard",
      "name": "Ancient elven ritual shard",
      "breakdownNotes": "",
      "label": "elvenshard",
      "selected": false
    },
    {
      "image": "https://i.imgur.com/KPREDHT.png",
      "wikiLink": "https://runescape.wiki/w/Charos'_clue_carrier",
      "name": "Charos' clue carrier",
      "breakdownNotes": "",
      "label": "cluebag",
      "selected": false
    },
    {
      "image": "",
      "name": "",
      "breakdownNotes": "",
      "label": "",
      "selected": false
    },
    {
      "image": "",
      "name": "",
      "breakdownNotes": "",
      "label": "",
      "selected": false
    },
    {
      "image": "",
      "name": "",
      "breakdownNotes": "",
      "label": "",
      "selected": false
    },
    {
      "image": "",
      "name": "",
      "breakdownNotes": "",
      "label": "",
      "selected": false
    },
    {
      "image": "https://i.imgur.com/hvhOeDs.png",
      "wikiLink": "https://runescape.wiki/w/Grasping_rune_pouch_(black)",
      "name": "Grasping rune pouch (black)",
      "breakdownNotes": "Blood | Astral | Body | Soul - Runes for <img class=\"disc-emoji\" src=\"https://cdn.discordapp.com/emojis/537338981747261446.png?v=1\" /> <img class=\"disc-emoji\" src=\"https://cdn.discordapp.com/emojis/856635090453135382.png?v=1\" />",
      "label": "graspingpouchblack",
      "selected": false
    },
    {
      "image": "",
      "name": "",
      "breakdownNotes": "",
      "label": "",
      "selected": false
    },
    {
      "image": "",
      "name": "",
      "breakdownNotes": "",
      "label": "",
      "selected": false
    },
    {
      "image": "",
      "name": "",
      "breakdownNotes": "",
      "label": "",
      "selected": false
    },
    {
      "image": "",
      "name": "",
      "breakdownNotes": "",
      "label": "",
      "selected": false
    },
    {
      "image": "",
      "name": "",
      "breakdownNotes": "",
      "label": "",
      "selected": false
    },
    {
      "image": "",
      "name": "",
      "breakdownNotes": "",
      "label": "",
      "selected": false
    },
    {
      "image": "https://i.imgur.com/gDZtYb4.png",
      "wikiLink": "https://runescape.wiki/w/Grasping_rune_pouch_(blue)",
      "name": "Grasping rune pouch (blue)",
      "breakdownNotes": "Chaos | Air | Water | Fire <span>- Runes for </span><img class=\"disc-emoji\" src=\"https://cdn.discordapp.com/emojis/537338981747261446.png?v=1\" /><span> </span><img class=\"disc-emoji\" src=\"https://cdn.discordapp.com/emojis/856635090453135382.png?v=1\" />",
      "label": "graspingpouchblue",
      "selected": false
    }
  ],
  "relics": {
    "primaryRelics": [
      {
        "image": "",
        "name": "",
        "breakdownNotes": "",
        "label": ""
      },
      {
        "image": "",
        "name": "",
        "breakdownNotes": "",
        "label": ""
      },
      {
        "image": "",
        "name": "",
        "breakdownNotes": "",
        "label": ""
      }
    ],
    "alternativeRelics": [
      {
        "image": "",
        "name": "",
        "breakdownNotes": "",
        "label": ""
      },
      {
        "image": "",
        "name": "",
        "breakdownNotes": "",
        "label": ""
      },
      {
        "image": "",
        "name": "",
        "breakdownNotes": "",
        "label": ""
      }
    ]
  },
  "familiars": {
    "alternativeFamiliars": [
      {
        "image": "",
        "name": "",
        "breakdownNotes": "",
        "label": ""
      },
      {
        "image": "",
        "name": "",
        "breakdownNotes": "",
        "label": ""
      },
      {
        "image": "",
        "name": "",
        "breakdownNotes": "",
        "label": ""
      }
    ],
    "primaryFamiliars": [
      {
        "image": "https://i.imgur.com/qbTjhXc.png",
        "name": "Smoke Nihil",
        "breakdownNotes": "",
        "label": "smokenihil"
      }
    ]
  }
}