{
  "presetName": "Ranged RotS",
  "presetNotes": "",
  "equipmentSlots": [
    {
      "image": "https://i.imgur.com/lhfAbhp.png",
      "wikiLink": "https://runescape.wiki/w/Sirenic_mask",
      "name": "Sirenic mask",
      "breakdownNotes": "",
      "label": "sirenichelm"
    },
    {
      "image": "https://i.imgur.com/TNKAuKX.png",
      "wikiLink": "https://runescape.wiki/w/Igneous_Kal-Xil",
      "name": "Igneous Kal-Xil",
      "breakdownNotes": "Can downgrade to Kiln cape or Defence skillcape.",
      "label": "kalxil"
    },
    {
      "image": "https://i.imgur.com/8a6M64a.png",
      "wikiLink": "https://runescape.wiki/w/Essence_of_Finality_amulet_(green)",
      "name": "Essence of Finality amulet (green)",
      "breakdownNotes": "Can be downgraded to Reaper Necklace.",
      "label": "eofgreenunorn"
    },
    {
      "image": "https://i.imgur.com/TMWKAqQ.png",
      "wikiLink": "https://runescape.wiki/w/Mechanised_chinchompa",
      "name": "Mechanised chinchompa",
      "breakdownNotes": "",
      "label": "chins"
    },
    {
      "image": "https://i.imgur.com/lYDKMiu.png",
      "wikiLink": "https://runescape.wiki/w/Sirenic_hauberk",
      "name": "Sirenic hauberk",
      "breakdownNotes": "",
      "label": "sirenictop"
    },
    {
      "image": "https://i.imgur.com/tSwe20M.png",
      "wikiLink": "https://runescape.wiki/w/Off-hand_ascension_crossbow",
      "name": "Off-hand ascension crossbow",
      "breakdownNotes": "",
      "label": "ohasc"
    },
    {
      "image": "https://i.imgur.com/gBPOqaV.png",
      "wikiLink": "https://runescape.wiki/w/Sirenic_chaps",
      "name": "Sirenic chaps",
      "breakdownNotes": "",
      "label": "sireniclegs"
    },
    {
      "image": "https://i.imgur.com/goMzH9N.png",
      "wikiLink": "https://runescape.wiki/w/Nightmare_gauntlets",
      "name": "Nightmare gauntlets",
      "breakdownNotes": "",
      "label": "nightmare"
    },
    {
      "image": "https://i.imgur.com/R5kSCvF.png",
      "wikiLink": "https://runescape.wiki/w/Fleeting_boots",
      "name": "Fleeting boots",
      "breakdownNotes": "",
      "label": "fleet"
    },
    {
      "image": "https://i.imgur.com/RZg5LNG.png",
      "wikiLink": "https://runescape.wiki/w/Asylum_surgeon's_ring",
      "name": "Asylum surgeon's ring",
      "breakdownNotes": "Upgrade to Stalker's Ring &gt; Reaver's Ring &gt; Ring of Death.",
      "label": "asr"
    },
    {
      "image": "https://i.imgur.com/xbNBoDV.png",
      "wikiLink": "https://runescape.wiki/w/Hydrix_bakriminel_bolts_(e)",
      "name": "Hydrix bakriminel bolts (e)",
      "breakdownNotes": "",
      "label": "hydrix"
    },
    {
      "image": "https://i.imgur.com/FZ59xZK.png",
      "wikiLink": "https://runescape.wiki/w/Reckless_aura",
      "name": "Reckless aura",
      "breakdownNotes": "",
      "label": "reckless"
    },
    {
      "image": "https://i.imgur.com/we1VPRx.png",
      "wikiLink": "https://runescape.wiki/w/Scrimshaw_of_Cruelty",
      "name": "Scrimshaw of Cruelty",
      "breakdownNotes": "",
      "label": "cruelty"
    }
  ],
  "inventorySlots": [
    {
      "image": "https://i.imgur.com/gIfjnhJ.png",
      "wikiLink": "https://runescape.wiki/w/Barrows_totems",
      "name": "Barrows totems",
      "breakdownNotes": "One required per kill.",
      "label": "barrowstotems"
    },
    {
      "image": "https://i.imgur.com/2vI8jNm.png",
      "wikiLink": "https://runescape.wiki/w/Vulnerabilty_bombs",
      "name": "Vulnerabilty bombs",
      "breakdownNotes": "",
      "label": "vuln"
    },
    {
      "image": "https://i.imgur.com/DGw6F36.png",
      "wikiLink": "https://runescape.wiki/w/Elder_overload#(6)",
      "name": "Elder overload potion (6)",
      "breakdownNotes": "",
      "label": "ovl"
    },
    {
      "image": "https://i.imgur.com/RD2LyxF.png",
      "wikiLink": "https://runescape.wiki/w/Blue_blubber_jellyfish",
      "name": "Blue blubber jellyfish",
      "breakdownNotes": "",
      "label": "jelly"
    },
    {
      "image": "https://i.imgur.com/RD2LyxF.png",
      "wikiLink": "https://runescape.wiki/w/Blue_blubber_jellyfish",
      "name": "Blue blubber jellyfish",
      "breakdownNotes": "",
      "label": "jelly"
    },
    {
      "image": "https://i.imgur.com/RD2LyxF.png",
      "wikiLink": "https://runescape.wiki/w/Blue_blubber_jellyfish",
      "name": "Blue blubber jellyfish",
      "breakdownNotes": "",
      "label": "jelly"
    },
    {
      "image": "https://i.imgur.com/RD2LyxF.png",
      "wikiLink": "https://runescape.wiki/w/Blue_blubber_jellyfish",
      "name": "Blue blubber jellyfish",
      "breakdownNotes": "",
      "label": "jelly"
    },
    {
      "image": "https://i.imgur.com/VZnA3ZS.png",
      "wikiLink": "https://runescape.wiki/w/Ascension_crossbow",
      "name": "Ascension crossbow",
      "breakdownNotes": "",
      "label": "asc"
    },
    {
      "image": "https://i.imgur.com/nC5xTAR.png",
      "wikiLink": "https://runescape.wiki/w/Enhanced_excalibur",
      "name": "Enhanced excalibur",
      "breakdownNotes": "",
      "label": "excal"
    },
    {
      "image": "https://i.imgur.com/IqAjWRF.png",
      "wikiLink": "https://runescape.wiki/w/Adrenaline_renewal_potion#(4)",
      "name": "Adrenaline renewal potion (4)",
      "breakdownNotes": "",
      "label": "renewal4"
    },
    {
      "image": "https://i.imgur.com/RD2LyxF.png",
      "wikiLink": "https://runescape.wiki/w/Blue_blubber_jellyfish",
      "name": "Blue blubber jellyfish",
      "breakdownNotes": "",
      "label": "jelly"
    },
    {
      "image": "https://i.imgur.com/RD2LyxF.png",
      "wikiLink": "https://runescape.wiki/w/Blue_blubber_jellyfish",
      "name": "Blue blubber jellyfish",
      "breakdownNotes": "",
      "label": "jelly"
    },
    {
      "image": "https://i.imgur.com/RD2LyxF.png",
      "wikiLink": "https://runescape.wiki/w/Blue_blubber_jellyfish",
      "name": "Blue blubber jellyfish",
      "breakdownNotes": "",
      "label": "jelly"
    },
    {
      "image": "https://i.imgur.com/RD2LyxF.png",
      "wikiLink": "https://runescape.wiki/w/Blue_blubber_jellyfish",
      "name": "Blue blubber jellyfish",
      "breakdownNotes": "",
      "label": "jelly"
    },
    {
      "image": "https://i.imgur.com/I6HFjyN.png",
      "wikiLink": "https://runescape.wiki/w/Powerburst_of_acceleration#(4)",
      "name": "Powerburst of acceleration (4)",
      "breakdownNotes": "",
      "label": "accel4"
    },
    {
      "image": "https://i.imgur.com/qocLc4k.png",
      "wikiLink": "https://runescape.wiki/w/Sailfish",
      "name": "Sailfish",
      "breakdownNotes": "",
      "label": "sailfish"
    },
    {
      "image": "https://i.imgur.com/qocLc4k.png",
      "wikiLink": "https://runescape.wiki/w/Sailfish",
      "name": "Sailfish",
      "breakdownNotes": "",
      "label": "sailfish"
    },
    {
      "image": "https://i.imgur.com/iXpGYQo.png",
      "wikiLink": "https://runescape.wiki/w/Guthix_rest",
      "name": "Guthix rest",
      "breakdownNotes": "",
      "label": "grest"
    },
    {
      "image": "https://i.imgur.com/iXpGYQo.png",
      "wikiLink": "https://runescape.wiki/w/Guthix_rest",
      "name": "Guthix rest",
      "breakdownNotes": "",
      "label": "grest"
    },
    {
      "image": "https://i.imgur.com/iXpGYQo.png",
      "wikiLink": "https://runescape.wiki/w/Guthix_rest",
      "name": "Guthix rest",
      "breakdownNotes": "",
      "label": "grest"
    },
    {
      "image": "https://i.imgur.com/iXpGYQo.png",
      "wikiLink": "https://runescape.wiki/w/Guthix_rest",
      "name": "Guthix rest",
      "breakdownNotes": "",
      "label": "grest"
    },
    null,
    null,
    null,
    null,
    null,
    null,
    null
  ],
  "relics": {
    "primaryRelics": [
      {
        "image": "https://i.imgur.com/xXWYCHG.png",
        "name": "Berserkers Fury",
        "breakdownNotes": "",
        "description": "Deal up to +5.5% damage (all styles) the lower your current life points are below max. (Doesn't stack with Dharok's set effect.)",
        "label": "berserkersfury",
        "energy": 250
      },
      {
        "image": "https://i.imgur.com/W87TO3O.png",
        "name": "Fury of the Small",
        "breakdownNotes": "",
        "description": "All adrenaline generating basic abilities generate +1% adrenaline.",
        "label": "furyofthesmall",
        "energy": 150
      },
      {
        "image": "",
        "name": "",
        "breakdownNotes": "",
        "label": ""
      }
    ],
    "alternativeRelics": [
      {
        "image": "",
        "name": "",
        "breakdownNotes": "",
        "label": ""
      },
      {
        "image": "",
        "name": "",
        "breakdownNotes": "",
        "label": ""
      },
      {
        "image": "",
        "name": "",
        "breakdownNotes": "",
        "label": ""
      }
    ]
  },
  "familiars": {
    "alternativeFamiliars": [
      {
        "image": "",
        "name": "",
        "breakdownNotes": "",
        "label": ""
      },
      {
        "image": "",
        "name": "",
        "breakdownNotes": "",
        "label": ""
      },
      {
        "image": "",
        "name": "",
        "breakdownNotes": "",
        "label": ""
      }
    ],
    "primaryFamiliars": [
      {
        "image": "https://i.imgur.com/Gg4oxrm.png",
        "name": "Ripper Demon",
        "breakdownNotes": "",
        "label": "ripperdemon"
      }
    ]
  }
}