{
  "presetName": "dyanne preset",
  "presetNotes": "",
  "equipmentSlots": [
    {
      "image": "https://i.imgur.com/5vasEy6.png",
      "wikiLink": "https://runescape.wiki/w/Deathwarden_hood_(tier_90)",
      "name": "Deathwarden hood (tier 90)",
      "breakdownNotes": "",
      "label": "deathwardenhoodt90"
    },
    {
      "image": "https://i.imgur.com/wTwgzck.png",
      "wikiLink": "https://runescape.wiki/w/Reefwalker's_cape",
      "name": "Reefwalker's cape",
      "breakdownNotes": "",
      "label": "reefcape"
    },
    {
      "image": "https://i.imgur.com/4KgPcpm.png",
      "wikiLink": "https://runescape.wiki/w/Grace_of_the_elves",
      "name": "Grace of the elves",
      "breakdownNotes": "",
      "label": "gote"
    },
    {
      "image": "https://i.imgur.com/FMf3ige.png",
      "wikiLink": "https://runescape.wiki/w/Wand_of_the_praesul_(shadow)",
      "name": "Wand of the praesul (shadow)",
      "breakdownNotes": "",
      "label": "pwandshadow"
    },
    {
      "image": "https://i.imgur.com/JkyJN48.png",
      "wikiLink": "https://runescape.wiki/w/Deathwarden_robe_top_(tier_90)",
      "name": "Deathwarden robe top (tier 90)",
      "breakdownNotes": "",
      "label": "deathwardenrobetopt90"
    },
    {
      "image": "https://i.imgur.com/ThpXK19.png",
      "wikiLink": "https://runescape.wiki/w/Merciless_kiteshield",
      "name": "Merciless kiteshield",
      "breakdownNotes": "",
      "label": "mageshield"
    },
    {
      "image": "https://i.imgur.com/4KirFLg.png",
      "wikiLink": "https://runescape.wiki/w/Deathwarden_robe_legs_(tier_90)",
      "name": "Deathwarden robe legs (tier 90)",
      "breakdownNotes": "",
      "label": "deathwardenrobelegst90"
    },
    {
      "image": "https://i.imgur.com/3WIoKQI.png",
      "wikiLink": "https://runescape.wiki/w/Deathwarden_gloves_(tier_90)",
      "name": "Deathwarden gloves (tier 90)",
      "breakdownNotes": "",
      "label": "deathwardenglovest90"
    },
    {
      "image": "https://i.imgur.com/V94Yora.png",
      "wikiLink": "https://runescape.wiki/w/Deathwarden_boots_(tier_90)",
      "name": "Deathwarden boots (tier 90)",
      "breakdownNotes": "",
      "label": "deathwardenbootst90"
    },
    {
      "image": "https://i.imgur.com/nXXZxpH.png",
      "wikiLink": "https://runescape.wiki/w/Luck_of_the_dwarves",
      "name": "Luck of the dwarves",
      "breakdownNotes": "",
      "label": "lotd"
    },
    {
      "image": "https://i.imgur.com/b3geFp8.png",
      "wikiLink": "https://runescape.wiki/w/Pernix's_Quiver",
      "name": "Pernix's Quiver",
      "breakdownNotes": "",
      "label": "pernixquiver"
    },
    {
      "image": "",
      "name": "",
      "breakdownNotes": "",
      "label": ""
    },
    {
      "image": "https://i.imgur.com/BQZgdnb.png",
      "wikiLink": "https://runescape.wiki/w/Grim_gem",
      "name": "Grim gem",
      "breakdownNotes": "",
      "label": "grimgem"
    }
  ],
  "inventorySlots": [
    {
      "image": "https://i.imgur.com/h5QEOgi.png",
      "wikiLink": "https://runescape.wiki/w/Divine_charge",
      "name": "Divine charge",
      "breakdownNotes": "",
      "label": "divcharge",
      "selected": false
    },
    {
      "image": "https://i.imgur.com/6GKoFBO.png",
      "wikiLink": "https://runescape.wiki/w/Ogre_flask_(thermal)",
      "name": "Ogre flask (thermal)",
      "breakdownNotes": "",
      "label": "ogrethermal",
      "selected": false
    },
    {
      "image": "https://i.imgur.com/9GP63eS.png",
      "wikiLink": "https://runescape.wiki/w/Elder_overload_salve#(6)",
      "name": "Elder overload salve (6)",
      "breakdownNotes": "",
      "label": "salve",
      "selected": false
    },
    {
      "image": "https://i.imgur.com/Ba7yju8.png",
      "wikiLink": "https://runescape.wiki/w/Kwuarm_incense_sticks",
      "name": "Kwuarm incense sticks",
      "breakdownNotes": "",
      "label": "kwuarmsticks",
      "selected": false
    },
    {
      "image": "https://i.imgur.com/oEYAJZf.png",
      "wikiLink": "https://runescape.wiki/w/Irit_incense_sticks",
      "name": "Irit incense sticks",
      "breakdownNotes": "",
      "label": "iritsticks",
      "selected": false
    },
    {
      "image": "https://i.imgur.com/BQXFPFu.png",
      "wikiLink": "https://runescape.wiki/w/Binding_contract_(blood_reaver)",
      "name": "Binding contract (blood reaver)",
      "breakdownNotes": "",
      "label": "reaver",
      "selected": false
    },
    {
      "image": "https://i.imgur.com/3o2DaTu.png",
      "wikiLink": "https://runescape.wiki/w/Blood_Reaver_scroll_(Blood_Siphon)",
      "name": "Blood Reaver scroll (Blood Siphon)",
      "breakdownNotes": "",
      "label": "reaverscrolls500",
      "selected": false
    },
    {
      "image": "https://i.imgur.com/Mk7jbjC.png",
      "wikiLink": "https://runescape.wiki/w/Grasping_rune_pouch",
      "name": "Grasping rune pouch",
      "breakdownNotes": "",
      "label": "graspingpouch",
      "selected": false
    },
    {
      "image": "https://i.imgur.com/7HrRTp8.png",
      "wikiLink": "https://runescape.wiki/w/Cosmic_rune",
      "name": "Cosmic rune",
      "breakdownNotes": "",
      "label": "cosmicrune",
      "selected": false
    },
    {
      "image": "https://i.imgur.com/PxjiQ9K.png",
      "wikiLink": "https://runescape.wiki/w/Astral_rune",
      "name": "Astral rune",
      "breakdownNotes": "",
      "label": "astralrune",
      "selected": false
    },
    {
      "image": "https://i.imgur.com/ILev8dS.png",
      "wikiLink": "https://runescape.wiki/w/Law_rune",
      "name": "Law rune",
      "breakdownNotes": "",
      "label": "lawrune",
      "selected": false
    },
    {
      "image": "https://i.imgur.com/orRGsqY.png",
      "wikiLink": "https://runescape.wiki/w/Body_rune",
      "name": "Body rune",
      "breakdownNotes": "",
      "label": "bodyrune",
      "selected": false
    },
    {
      "image": "https://i.imgur.com/5dumsv0.png",
      "wikiLink": "https://runescape.wiki/w/Binding_contract_(kal'gerion_demon)",
      "name": "Binding contract (kal'gerion demon)",
      "breakdownNotes": "",
      "label": "kalg",
      "selected": false
    },
    {
      "image": "https://i.imgur.com/hjoH9xr.png",
      "wikiLink": "https://runescape.wiki/w/Kal%27gerion_Demon_scroll_(Crit-i-Kal)",
      "name": "Kal'gerion Demon scroll (Crit-i-Kal)",
      "breakdownNotes": "",
      "label": "kalgscrolls500",
      "selected": false
    },
    {
      "image": "https://i.imgur.com/gCf8SPg.png",
      "wikiLink": "https://runescape.wiki/w/Grasping_rune_pouch_(purple)",
      "name": "Grasping rune pouch (purple)",
      "breakdownNotes": "",
      "label": "graspingpouchpurple",
      "selected": false
    },
    {
      "image": "https://i.imgur.com/0V4quVU.png",
      "wikiLink": "https://runescape.wiki/w/Death_rune",
      "name": "Death rune",
      "breakdownNotes": "",
      "label": "deathrune",
      "selected": false
    },
    {
      "image": "https://i.imgur.com/AnzJigr.png",
      "wikiLink": "https://runescape.wiki/w/Earth_rune",
      "name": "Earth rune",
      "breakdownNotes": "",
      "label": "earthrune",
      "selected": false
    },
    {
      "image": "https://i.imgur.com/hXWHlfs.png",
      "wikiLink": "https://runescape.wiki/w/Soul_rune",
      "name": "Soul rune",
      "breakdownNotes": "",
      "label": "soulrune",
      "selected": false
    },
    {
      "image": "https://i.imgur.com/DmJhw50.png",
      "wikiLink": "https://runescape.wiki/w/Blood_rune",
      "name": "Blood rune",
      "breakdownNotes": "",
      "label": "bloodrune",
      "selected": false
    },
    {
      "image": "https://i.imgur.com/FPfRiAQ.png",
      "wikiLink": "https://runescape.wiki/w/Binding_contract_(hellhound)",
      "name": "Binding contract (hellhound)",
      "breakdownNotes": "",
      "label": "hellhound",
      "selected": false
    },
    {
      "image": "https://i.imgur.com/rB1tPpW.png",
      "wikiLink": "https://runescape.wiki/w/Hellhound_scroll_(Soul_Food)",
      "name": "Hellhound scroll (Soul Food)",
      "breakdownNotes": "",
      "label": "hellhoundscrolls500",
      "selected": false
    },
    {
      "image": "https://i.imgur.com/hvhOeDs.png",
      "wikiLink": "https://runescape.wiki/w/Grasping_rune_pouch_(black)",
      "name": "Grasping rune pouch (black)",
      "breakdownNotes": "",
      "label": "graspingpouchblack",
      "selected": false
    },
    {
      "image": "https://i.imgur.com/9Nngfvj.png",
      "wikiLink": "https://runescape.wiki/w/Air_rune",
      "name": "Air rune",
      "breakdownNotes": "",
      "label": "airrune",
      "selected": false
    },
    {
      "image": "https://i.imgur.com/Moq1ANC.png",
      "wikiLink": "https://runescape.wiki/w/Fire_rune",
      "name": "Fire rune",
      "breakdownNotes": "",
      "label": "firerune",
      "selected": false
    },
    {
      "image": "https://i.imgur.com/VmHx4CQ.png",
      "wikiLink": "https://runescape.wiki/w/Chaos_rune",
      "name": "Chaos rune",
      "breakdownNotes": "",
      "label": "chaosrune",
      "selected": false
    },
    {
      "image": "https://i.imgur.com/WnPH1nm.png",
      "wikiLink": "https://runescape.wiki/w/Water_rune",
      "name": "Water rune",
      "breakdownNotes": "",
      "label": "waterrune",
      "selected": false
    },
    {
      "image": "https://i.imgur.com/eAO0PdY.png",
      "wikiLink": "https://runescape.wiki/w/Erethdor's_grimoire",
      "name": "Erethdor's grimoire",
      "breakdownNotes": "",
      "label": "grim",
      "selected": false
    },
    {
      "image": "https://i.imgur.com/KopqFpb.png",
      "wikiLink": "https://runescape.wiki/w/Torn_grimoire_page",
      "name": "Torn grimoire page",
      "breakdownNotes": "",
      "label": "grimpage10",
      "selected": false
    }
  ],
  "relics": {
    "primaryRelics": [
      {
        "image": "",
        "name": "",
        "breakdownNotes": "",
        "label": ""
      },
      {
        "image": "",
        "name": "",
        "breakdownNotes": "",
        "label": ""
      },
      {
        "image": "",
        "name": "",
        "breakdownNotes": "",
        "label": ""
      }
    ],
    "alternativeRelics": [
      {
        "image": "",
        "name": "",
        "breakdownNotes": "",
        "label": ""
      },
      {
        "image": "",
        "name": "",
        "breakdownNotes": "",
        "label": ""
      },
      {
        "image": "",
        "name": "",
        "breakdownNotes": "",
        "label": ""
      }
    ]
  },
  "familiars": {
    "alternativeFamiliars": [
      {
        "image": "",
        "name": "",
        "breakdownNotes": "",
        "label": ""
      },
      {
        "image": "",
        "name": "",
        "breakdownNotes": "",
        "label": ""
      },
      {
        "image": "",
        "name": "",
        "breakdownNotes": "",
        "label": ""
      }
    ],
    "primaryFamiliars": [
      {
        "image": "",
        "name": "",
        "breakdownNotes": "",
        "label": ""
      }
    ]
  }
}