{
  "presetName": "KK - Duo (DPS)",
  "presetNotes": "",
  "equipmentSlots": [
    {
      "image": "https://i.imgur.com/EVh5SwD.png",
      "wikiLink": "https://runescape.wiki/w/Vestments_of_havoc_hood",
      "name": "Vestments of havoc hood",
      "breakdownNotes": "",
      "label": "vestmenthood"
    },
    {
      "image": "https://i.imgur.com/bfzX8Up.png",
      "wikiLink": "https://runescape.wiki/w/Igneous_Kal-Ket",
      "name": "Igneous Kal-Ket",
      "breakdownNotes": "",
      "label": "kalket"
    },
    {
      "image": "https://i.imgur.com/JInu2Jy.png",
      "wikiLink": "https://runescape.wiki/w/Desert_amulet_4",
      "name": "Desert amulet 4",
      "breakdownNotes": "",
      "label": "desertamulet4"
    },
    {
      "image": "https://i.imgur.com/wFdHN9C.png",
      "wikiLink": "https://runescape.wiki/w/Dark_Shard_of_Leng",
      "name": "Dark Shard of Leng",
      "breakdownNotes": "",
      "label": "lengmh"
    },
    {
      "image": "https://i.imgur.com/E5ptfu6.png",
      "wikiLink": "https://runescape.wiki/w/Vestments_of_havoc_robe_top",
      "name": "Vestments of havoc robe top",
      "breakdownNotes": "",
      "label": "vestmentbody"
    },
    {
      "image": "https://i.imgur.com/LAVYvrE.png",
      "wikiLink": "https://runescape.wiki/w/Dark_Sliver_of_Leng",
      "name": "Dark Sliver of Leng",
      "breakdownNotes": "",
      "label": "lengoh"
    },
    {
      "image": "https://i.imgur.com/mz7GwWF.png",
      "wikiLink": "https://runescape.wiki/w/Vestments_of_havoc_robe_bottom",
      "name": "Vestments of havoc robe bottom",
      "breakdownNotes": "",
      "label": "vestmentlegs"
    },
    {
      "image": "https://i.imgur.com/U4Wa7vb.png",
      "wikiLink": "https://runescape.wiki/w/Gloves_of_passage",
      "name": "Gloves of passage",
      "breakdownNotes": "",
      "label": "glovesofpassage"
    },
    {
      "image": "https://i.imgur.com/FarIA5V.png",
      "wikiLink": "https://runescape.wiki/w/Vestments_of_havoc_boots",
      "name": "Vestments of havoc boots",
      "breakdownNotes": "",
      "label": "vestmentboots"
    },
    {
      "image": "https://i.imgur.com/cc9GxHt.png",
      "wikiLink": "https://runescape.wiki/w/Champion's_ring",
      "name": "Champion's ring",
      "breakdownNotes": "",
      "label": "championring"
    },
    {
      "image": "https://i.imgur.com/cevmcA1.png",
      "wikiLink": "https://runescape.wiki/w/Abyssal_armour_spikes_(alloy)",
      "name": "Abyssal armour spikes (alloy)",
      "breakdownNotes": "",
      "label": "abyssalspikes"
    },
    {
      "image": "https://i.imgur.com/dNm4A5W.png",
      "wikiLink": "https://runescape.wiki/w/Berserker_aura",
      "name": "Berserker aura",
      "breakdownNotes": "",
      "label": "zerk"
    },
    {
      "image": "https://i.imgur.com/FAPSk6p.png",
      "wikiLink": "https://runescape.wiki/w/Erethdor's_grimoire",
      "name": "Erethdor's grimoire",
      "breakdownNotes": "",
      "label": "grim"
    }
  ],
  "inventorySlots": [
    {
      "image": "https://i.imgur.com/m8aQij5.png",
      "wikiLink": "https://runescape.wiki/w/Masterwork_spear_of_annihilation",
      "name": "Masterwork spear of annihilation",
      "breakdownNotes": "",
      "label": "spear",
      "selected": false
    },
    {
      "image": "https://i.imgur.com/LutTgCH.png",
      "wikiLink": "https://runescape.wiki/w/Cinderbane_gloves",
      "name": "Cinderbane gloves",
      "breakdownNotes": "",
      "label": "cinder",
      "selected": false
    },
    {
      "image": "https://i.imgur.com/JMC7t7Y.png",
      "wikiLink": "https://runescape.wiki/w/EoF_-_Dragon_claws",
      "name": "EoF - Dragon claws",
      "breakdownNotes": "",
      "label": "eofred",
      "selected": false
    },
    {
      "image": "https://i.imgur.com/pzEjejy.png",
      "wikiLink": "https://runescape.wiki/w/Elder_overload",
      "name": "Elder overload",
      "breakdownNotes": "",
      "label": "ovl",
      "selected": false
    },
    {
      "image": "https://i.imgur.com/5PPmPXC.png",
      "wikiLink": "https://runescape.wiki/w/Spiritual_prayer",
      "name": "Spiritual prayer",
      "breakdownNotes": "",
      "label": "spiritual",
      "selected": false
    },
    {
      "image": "https://i.imgur.com/5PPmPXC.png",
      "wikiLink": "https://runescape.wiki/w/Spiritual_prayer",
      "name": "Spiritual prayer",
      "breakdownNotes": "",
      "label": "spiritual",
      "selected": false
    },
    {
      "image": "https://i.imgur.com/5PPmPXC.png",
      "wikiLink": "https://runescape.wiki/w/Spiritual_prayer",
      "name": "Spiritual prayer",
      "breakdownNotes": "",
      "label": "spiritual",
      "selected": false
    },
    {
      "image": "https://i.imgur.com/vxMoCyg.png",
      "wikiLink": "https://runescape.wiki/w/Malevolent_greaves",
      "name": "Malevolent greaves",
      "breakdownNotes": "Clear Headed 4 switch.",
      "label": "malevlegs",
      "selected": false
    },
    {
      "image": "https://i.imgur.com/AQnrzP2.png",
      "wikiLink": "https://runescape.wiki/w/Keris",
      "name": "Keris",
      "breakdownNotes": "",
      "label": "keris",
      "selected": false
    },
    {
      "selected": false
    },
    {
      "image": "https://i.imgur.com/b7OFnll.png",
      "wikiLink": "https://runescape.wiki/w/Adrenaline_renewal",
      "name": "Adrenaline renewal",
      "breakdownNotes": "",
      "label": "renewal4",
      "selected": false
    },
    {
      "image": "https://i.imgur.com/ygwcjzt.png",
      "wikiLink": "https://runescape.wiki/w/Blue_blubber_jellyfish",
      "name": "Blue blubber jellyfish",
      "breakdownNotes": "",
      "label": "jelly",
      "selected": false
    },
    {
      "image": "https://i.imgur.com/ygwcjzt.png",
      "wikiLink": "https://runescape.wiki/w/Blue_blubber_jellyfish",
      "name": "Blue blubber jellyfish",
      "breakdownNotes": "",
      "label": "jelly",
      "selected": false
    },
    {
      "image": "https://i.imgur.com/ygwcjzt.png",
      "wikiLink": "https://runescape.wiki/w/Blue_blubber_jellyfish",
      "name": "Blue blubber jellyfish",
      "breakdownNotes": "",
      "label": "jelly",
      "selected": false
    },
    {
      "selected": false
    },
    {
      "selected": false
    },
    {
      "selected": false
    },
    {
      "image": "https://i.imgur.com/hw7rKHz.png",
      "wikiLink": "https://runescape.wiki/w/Weapon_poison+++_(1_dose)",
      "name": "Weapon poison+++ (1 dose)",
      "breakdownNotes": "",
      "label": "poison1",
      "selected": false
    },
    {
      "image": "https://i.imgur.com/ygwcjzt.png",
      "wikiLink": "https://runescape.wiki/w/Blue_blubber_jellyfish",
      "name": "Blue blubber jellyfish",
      "breakdownNotes": "",
      "label": "jelly",
      "selected": false
    },
    {
      "image": "https://i.imgur.com/ygwcjzt.png",
      "wikiLink": "https://runescape.wiki/w/Blue_blubber_jellyfish",
      "name": "Blue blubber jellyfish",
      "breakdownNotes": "",
      "label": "jelly",
      "selected": false
    },
    {
      "image": "https://i.imgur.com/ygwcjzt.png",
      "wikiLink": "https://runescape.wiki/w/Blue_blubber_jellyfish",
      "name": "Blue blubber jellyfish",
      "breakdownNotes": "",
      "label": "jelly",
      "selected": false
    },
    {
      "image": "https://i.imgur.com/hvhOeDs.png",
      "wikiLink": "https://runescape.wiki/w/Grasping_rune_pouch_(black)",
      "name": "Grasping rune pouch (black)",
      "breakdownNotes": "Blood | Astral | Body | Soul",
      "label": "graspingpouchblack",
      "selected": false
    },
    {
      "image": "https://i.imgur.com/yrnlR2T.png",
      "wikiLink": "https://runescape.wiki/w/Grasping_rune_pouch_(pink)",
      "name": "Grasping rune pouch (pink)",
      "breakdownNotes": "Death | Earth | Law | Cosmic",
      "label": "graspingpouchpink",
      "selected": false
    },
    {
      "selected": false
    },
    {
      "image": "https://i.imgur.com/306PXtG.png",
      "wikiLink": "https://runescape.wiki/w/Vulnerabilty_bombs",
      "name": "Vulnerabilty bombs",
      "breakdownNotes": "",
      "label": "vuln",
      "selected": false
    },
    {
      "image": "https://i.imgur.com/U47oHsq.png",
      "wikiLink": "https://runescape.wiki/w/Guthix_rest",
      "name": "Guthix rest",
      "breakdownNotes": "",
      "label": "grest",
      "selected": false
    },
    {
      "image": "https://i.imgur.com/U47oHsq.png",
      "wikiLink": "https://runescape.wiki/w/Guthix_rest",
      "name": "Guthix rest",
      "breakdownNotes": "",
      "label": "grest",
      "selected": false
    },
    {
      "image": "https://i.imgur.com/U47oHsq.png",
      "wikiLink": "https://runescape.wiki/w/Guthix_rest",
      "name": "Guthix rest",
      "breakdownNotes": "",
      "label": "grest",
      "selected": false
    }
  ],
  "relics": {
    "primaryRelics": [
      {
        "image": "https://i.imgur.com/Gfdc9u6.png",
        "name": "Conservation of Energy",
        "breakdownNotes": "",
        "label": "conservationofenergy",
        "energy": 350
      },
      {
        "image": "https://i.imgur.com/W87TO3O.png",
        "name": "Fury of the Small",
        "breakdownNotes": "",
        "label": "furyofthesmall",
        "energy": 150
      },
      {
        "image": "https://i.imgur.com/cFlJmWP.png",
        "name": "Death Ward",
        "breakdownNotes": "",
        "label": "deathward",
        "energy": 150
      }
    ],
    "alternativeRelics": [
      {
        "image": "",
        "name": "",
        "breakdownNotes": "",
        "label": ""
      },
      {
        "image": "",
        "name": "",
        "breakdownNotes": "",
        "label": ""
      },
      {
        "image": "",
        "name": "",
        "breakdownNotes": "",
        "label": ""
      }
    ]
  },
  "familiars": {
    "alternativeFamiliars": [
      {
        "image": "",
        "name": "",
        "breakdownNotes": "",
        "label": ""
      },
      {
        "image": "",
        "name": "",
        "breakdownNotes": "",
        "label": ""
      },
      {
        "image": "",
        "name": "",
        "breakdownNotes": "",
        "label": ""
      }
    ],
    "primaryFamiliars": [
      {
        "image": "https://i.imgur.com/Gg4oxrm.png",
        "name": "Ripper Demon",
        "breakdownNotes": "",
        "label": "ripperdemon"
      }
    ]
  }
}