{
  "presetName": "AFK Kalgerion Demons POSD",
  "presetNotes": "x3 Kal'gerions in POSD<br />Protect from Melee + Ruination",
  "equipmentSlots": [
    {
      "image": "https://i.imgur.com/2msk92n.png",
      "wikiLink": "https://runescape.wiki/w/Crown_of_the_First_Necromancer",
      "name": "Crown of the First Necromancer",
      "breakdownNotes": "",
      "label": "t95necrohelm"
    },
    {
      "image": "https://i.imgur.com/jcfkzGn.png",
      "wikiLink": "https://runescape.wiki/w/Igneous_Kal-Zuk",
      "name": "Igneous Kal-Zuk",
      "breakdownNotes": "",
      "label": "kalzuk"
    },
    {
      "image": "https://i.imgur.com/gA1MFTE.png",
      "wikiLink": "https://runescape.wiki/w/Demon_horn_necklace",
      "name": "Demon horn necklace",
      "breakdownNotes": "Prayer Sustain",
      "label": "demonhorn"
    },
    {
      "image": "https://i.imgur.com/SzFvoQB.png",
      "wikiLink": "https://runescape.wiki/w/Omni_guard",
      "name": "Omni guard",
      "breakdownNotes": "Aftershock 4, Eruptive 2",
      "label": "omniguard"
    },
    {
      "image": "https://i.imgur.com/VwEHIYQ.png",
      "wikiLink": "https://runescape.wiki/w/Robe_top_of_the_First_Necromancer",
      "name": "Robe top of the First Necromancer",
      "breakdownNotes": "Relentless 5, Crackling 4 | Biting 4, Mobile",
      "label": "t95necrotop"
    },
    {
      "image": "https://i.imgur.com/VJsZ4HL.png",
      "wikiLink": "https://runescape.wiki/w/Soulbound_lantern",
      "name": "Soulbound lantern",
      "breakdownNotes": "Precise 6, Aftershock 1",
      "label": "soulboundlantern"
    },
    {
      "image": "https://i.imgur.com/s0Acz4g.png",
      "wikiLink": "https://runescape.wiki/w/Robe_bottom_of_the_First_Necromancer",
      "name": "Robe bottom of the First Necromancer",
      "breakdownNotes": "Devoted 4, Impatient 4 | Invigorating 4, Demon Slayer",
      "label": "t95necrolegs"
    },
    {
      "image": "https://i.imgur.com/8zjLczG.png",
      "wikiLink": "https://runescape.wiki/w/Hand_wrap_of_the_First_Necromancer",
      "name": "Hand wrap of the First Necromancer",
      "breakdownNotes": "",
      "label": "t95necrogloves"
    },
    {
      "image": "https://i.imgur.com/FawdniP.png",
      "wikiLink": "https://runescape.wiki/w/Foot_wraps_of_the_First_Necromancer",
      "name": "Foot wraps of the First Necromancer",
      "breakdownNotes": "",
      "label": "t95necroboots"
    },
    {
      "image": "https://i.imgur.com/xmcbfhs.png",
      "wikiLink": "https://runescape.wiki/w/Hazelmere's_signet",
      "name": "Hazelmere's signet ring",
      "breakdownNotes": "Increased Rare drop chance",
      "label": "hsr"
    },
    {
      "image": "https://i.imgur.com/3pFXvMR.png",
      "wikiLink": "https://runescape.wiki/w/Zemouregal%27s_nexus",
      "name": "Zemoregal's Nexus",
      "breakdownNotes": "Runes for Darkness",
      "label": "zemouregalsnexus"
    },
    {
      "image": "https://i.imgur.com/br11PCq.png",
      "wikiLink": "https://runescape.wiki/w/Mahjarrat_aura",
      "name": "Mahjarrat aura",
      "breakdownNotes": "Any aura will do",
      "label": "mahj"
    },
    {
      "image": "https://i.imgur.com/lPppoD4.png",
      "wikiLink": "https://runescape.wiki/w/Scripture_of_Ful",
      "name": "Scripture of Ful",
      "breakdownNotes": "More damage",
      "label": "scriptureofful"
    }
  ],
  "inventorySlots": [
    {
      "image": "https://i.imgur.com/DGw6F36.png",
      "wikiLink": "https://runescape.wiki/w/Elder_overload#(6)",
      "name": "Elder overload potion (6)",
      "breakdownNotes": "Overloads",
      "label": "ovl",
      "selected": false
    },
    {
      "image": "https://i.imgur.com/nTRsMW1.png",
      "wikiLink": "https://runescape.wiki/w/Aggression_flask#(6)",
      "name": "Aggression flask (6)",
      "breakdownNotes": "Keep active at all times",
      "label": "aggro6",
      "selected": false
    },
    {
      "image": "https://i.imgur.com/KkIYNhk.png",
      "wikiLink": "https://runescape.wiki/w/Binding_contracts",
      "name": "Binding contracts",
      "breakdownNotes": "To make Kal'gerion pouches",
      "label": "contracts",
      "selected": false
    },
    {
      "selected": false
    },
    {
      "image": "",
      "name": "",
      "breakdownNotes": "",
      "label": "",
      "selected": false
    },
    {
      "image": "https://i.imgur.com/MivUk5T.png",
      "wikiLink": "https://runescape.wiki/w/Slayer_codex",
      "name": "Slayer codex",
      "breakdownNotes": "Teleport to POSD",
      "label": "scodex",
      "selected": false
    },
    {
      "image": "https://i.imgur.com/LfpiRjg.png",
      "wikiLink": "https://runescape.wiki/w/Lantadyme_incense_sticks",
      "name": "Lantadyme incense sticks",
      "breakdownNotes": "Increased Overload timer",
      "label": "lantasticks",
      "selected": false
    },
    {
      "image": "https://i.imgur.com/nC5xTAR.png",
      "wikiLink": "https://runescape.wiki/w/Enhanced_excalibur",
      "name": "Enhanced excalibur",
      "breakdownNotes": "Extra HP (Optional)",
      "label": "excal",
      "selected": false
    },
    {
      "image": "",
      "name": "",
      "breakdownNotes": "",
      "label": "",
      "selected": false
    },
    {
      "selected": false
    },
    {
      "selected": false
    },
    {
      "selected": false
    },
    {
      "selected": false
    },
    {
      "selected": false
    },
    {
      "selected": false
    },
    {
      "selected": false
    },
    {
      "selected": false
    },
    {
      "selected": false
    },
    {
      "selected": false
    },
    {
      "selected": false
    },
    {
      "selected": false
    },
    {
      "image": "https://i.imgur.com/pjHPdhj.png",
      "wikiLink": "https://runescape.wiki/w/Spring_cleaner_9001",
      "name": "Spring cleaner 9001",
      "breakdownNotes": "",
      "label": "springcleaner",
      "selected": false
    },
    {
      "image": "https://i.imgur.com/NkIcFSt.png",
      "wikiLink": "https://runescape.wiki/w/Attuned_ectoplasmator",
      "name": "Attuned ectoplasmator",
      "breakdownNotes": "Prayer Sustain",
      "label": "ecto",
      "selected": false
    },
    {
      "image": "https://i.imgur.com/8r07LbS.png",
      "wikiLink": "https://runescape.wiki/w/Magic_notepaper",
      "name": "Magic notepaper",
      "breakdownNotes": "Note Binding Contracts",
      "label": "1knote",
      "selected": false
    },
    {
      "selected": false
    },
    {
      "selected": false
    },
    {
      "image": "https://i.imgur.com/JujxNhC.png",
      "wikiLink": "https://runescape.wiki/w/Seed_bag",
      "name": "Seed bag",
      "breakdownNotes": "Stores seeds",
      "label": "seedbag",
      "selected": false
    },
    {
      "image": "https://i.imgur.com/egmZjv0.png",
      "wikiLink": "https://runescape.wiki/w/Herb_bag",
      "name": "Herb bag",
      "breakdownNotes": "Stores herbs",
      "label": "herbbag",
      "selected": false
    }
  ],
  "relics": {
    "primaryRelics": [
      {
        "image": "https://i.imgur.com/W87TO3O.png",
        "name": "Fury of the Small",
        "breakdownNotes": "",
        "description": "All adrenaline generating basic abilities generate +1% adrenaline.",
        "label": "furyofthesmall",
        "energy": 150
      },
      {
        "image": "https://i.imgur.com/cFlJmWP.png",
        "name": "Death Ward",
        "breakdownNotes": "",
        "description": "5% damage reduction when your life points are below 50%; 10% damage reduction when they are below 25%.",
        "label": "deathward",
        "energy": 150
      },
      {
        "image": "https://i.imgur.com/Gfdc9u6.png",
        "name": "Conservation of Energy",
        "breakdownNotes": "",
        "description": "After using an ultimate ability, you will regain 10% adrenaline.",
        "label": "conservationofenergy",
        "energy": 350
      }
    ],
    "alternativeRelics": [
      {
        "image": "",
        "name": "",
        "breakdownNotes": "",
        "label": ""
      },
      {
        "image": "",
        "name": "",
        "breakdownNotes": "",
        "label": ""
      },
      {
        "image": "",
        "name": "",
        "breakdownNotes": "",
        "label": ""
      }
    ]
  },
  "familiars": {
    "alternativeFamiliars": [
      {
        "image": "",
        "name": "",
        "breakdownNotes": "",
        "label": ""
      },
      {
        "image": "",
        "name": "",
        "breakdownNotes": "",
        "label": ""
      },
      {
        "image": "",
        "name": "",
        "breakdownNotes": "",
        "label": ""
      }
    ],
    "primaryFamiliars": [
      {
        "image": "https://i.imgur.com/PXt50t7.png",
        "name": "Ice Nihil",
        "breakdownNotes": "",
        "label": "icenihil"
      }
    ]
  }
}