{
  "presetName": "",
  "presetNotes": "1. Use <img class=\"disc-emoji\" src=\"https://cdn.discordapp.com/emojis/537340400185245701.png?v=1\" /><span> +</span> <img class=\"disc-emoji\" src=\"https://cdn.discordapp.com/emojis/856662355952795658.png?v=1\" /> <span>or </span><img class=\"disc-emoji\" src=\"https://cdn.discordapp.com/emojis/856662355912032256.png?v=1\" /> on mobs not immune to roots to build adren if needed.",
  "equipmentSlots": [
    {
      "image": "https://i.imgur.com/PYRyglW.png",
      "wikiLink": "https://runescape.wiki/w/Mask_of_the_Ganodermic",
      "name": "Mask of the Ganodermic",
      "breakdownNotes": "Can be any other slayer mask for a creature that appears in RoB such as (Airut, Automaton) - Gives some bonus damage",
      "label": "maskoftheganodermic"
    },
    {
      "image": "https://i.imgur.com/jcfkzGn.png",
      "wikiLink": "https://runescape.wiki/w/Igneous_Kal-Zuk",
      "name": "Igneous Kal-Zuk",
      "breakdownNotes": "",
      "label": "kalzuk"
    },
    {
      "image": "https://i.imgur.com/nu7QSbh.png",
      "wikiLink": "https://runescape.wiki/w/Guthix_staff",
      "name": "EoF - Guthix staff",
      "breakdownNotes": "",
      "label": "eofpurple"
    },
    {
      "image": "https://i.imgur.com/WTkwmcP.png",
      "wikiLink": "https://runescape.wiki/w/Seismic_wand",
      "name": "Seismic wand",
      "breakdownNotes": "Can be substituted with <img class=\"disc-emoji\" src=\"https://cdn.discordapp.com/emojis/643161591571021824.png?v=1\" />",
      "label": "swand"
    },
    {
      "image": "https://i.imgur.com/84rL2dv.png",
      "wikiLink": "https://runescape.wiki/w/Anima_core_body_of_seren",
      "name": "Anima core body of seren",
      "breakdownNotes": "",
      "label": "serenbody"
    },
    {
      "image": "https://i.imgur.com/9c6iVBM.png",
      "wikiLink": "https://runescape.wiki/w/Elite_seasinger_makigai",
      "name": "Elite seasinger makigai",
      "breakdownNotes": "With E4R3 <img class=\"disc-emoji\" src=\"https://cdn.discordapp.com/emojis/712073088589627505.png?v=1\" /> <img class=\"disc-emoji\" src=\"https://cdn.discordapp.com/emojis/712244800572883025.png?v=1\" />,  <img class=\"disc-emoji\" src=\"https://cdn.discordapp.com/emojis/643161591210049556.png?v=1\" /> also viable",
      "label": "emakigai"
    },
    {
      "image": "https://i.imgur.com/I5QHqtm.png",
      "wikiLink": "https://runescape.wiki/w/Anima_core_legs_of_seren",
      "name": "Anima core legs of seren",
      "breakdownNotes": "",
      "label": "serenlegs"
    },
    {
      "image": "https://i.imgur.com/LutTgCH.png",
      "wikiLink": "https://runescape.wiki/w/Cinderbane_gloves",
      "name": "Cinderbane gloves",
      "breakdownNotes": "",
      "label": "cinder"
    },
    {
      "image": "https://i.imgur.com/2VPk1SN.png",
      "wikiLink": "https://runescape.wiki/w/Blast_diffusion_boots",
      "name": "Blast diffusion boots",
      "breakdownNotes": "Can also use silverhawk boots",
      "label": "diffusion"
    },
    {
      "image": "https://i.imgur.com/y5vAY4M.png",
      "wikiLink": "https://runescape.wiki/w/Ring_of_death",
      "name": "Ring of death",
      "breakdownNotes": "",
      "label": "rod"
    },
    {
      "image": "https://i.imgur.com/hvhOeDs.png",
      "wikiLink": "https://runescape.wiki/w/Grasping_rune_pouch_(black)",
      "name": "Grasping rune pouch (black)",
      "breakdownNotes": "Blood | Astral | Body | Soul - <img class=\"disc-emoji\" src=\"https://cdn.discordapp.com/emojis/856635090745950258.png?v=1\" /><span> </span><img class=\"disc-emoji\" src=\"https://cdn.discordapp.com/emojis/537340400185245701.png?v=1\" /> <img class=\"disc-emoji\" src=\"https://cdn.discordapp.com/emojis/537338981747261446.png?v=1\" />",
      "label": "graspingpouchblack"
    },
    {
      "image": "https://i.imgur.com/WB5GErF.png",
      "wikiLink": "https://runescape.wiki/w/Maniacal_aura",
      "name": "Maniacal aura",
      "breakdownNotes": "No aura is required, but <img class=\"disc-emoji\" src=\"https://cdn.discordapp.com/emojis/643505153709965322.png?v=1\" /> or <img class=\"disc-emoji\" src=\"https://cdn.discordapp.com/emojis/643505377211842582.png?v=1\" /> would be best for high defence monsters such as Airut or Kal'gerion demons",
      "label": "mani"
    },
    {
      "image": "https://i.imgur.com/lPppoD4.png",
      "wikiLink": "https://runescape.wiki/w/Scripture_of_Ful",
      "name": "Scripture of Ful",
      "breakdownNotes": "",
      "label": "scriptureofful"
    }
  ],
  "inventorySlots": [
    {
      "image": "https://i.imgur.com/9GP63eS.png",
      "wikiLink": "https://runescape.wiki/w/Elder_overload_salve#(6)",
      "name": "Elder overload salve (6)",
      "breakdownNotes": "",
      "label": "salve",
      "selected": false
    },
    {
      "image": "https://i.imgur.com/CR06fbn.png",
      "wikiLink": "https://runescape.wiki/w/Weapon_poison+++#(4)",
      "name": "Weapon poison+++ (4)",
      "breakdownNotes": "",
      "label": "poison4",
      "selected": false
    },
    {
      "image": "https://i.imgur.com/UVffd75.png",
      "wikiLink": "https://runescape.wiki/w/Holy_wrench",
      "name": "Holy wrench",
      "breakdownNotes": "",
      "label": "wrench",
      "selected": false
    },
    {
      "image": "https://i.imgur.com/buHbsri.png",
      "wikiLink": "https://runescape.wiki/w/Caroming_perk",
      "name": "Caroming perk",
      "breakdownNotes": "Specifically for the Jadinko wave, not essential",
      "label": "caroming",
      "selected": false
    },
    {
      "image": "",
      "name": "",
      "breakdownNotes": "",
      "label": "",
      "selected": false
    },
    {
      "image": "",
      "name": "",
      "breakdownNotes": "",
      "label": "",
      "selected": false
    },
    {
      "image": "",
      "name": "",
      "breakdownNotes": "",
      "label": "",
      "selected": false
    },
    {
      "image": "https://i.imgur.com/Swtl8pP.png",
      "wikiLink": "https://runescape.wiki/w/Adrenaline_renewal_flask#(6)",
      "name": "Adrenaline renewal flask (6)",
      "breakdownNotes": "",
      "label": "renewal6",
      "selected": false
    },
    {
      "image": "https://i.imgur.com/2uy0pnb.png",
      "wikiLink": "https://runescape.wiki/w/Super_restore_flask#(6)",
      "name": "Super restore flask (6)",
      "breakdownNotes": "",
      "label": "restore",
      "selected": false
    },
    {
      "image": "https://i.imgur.com/SOBvbj7.png",
      "wikiLink": "https://runescape.wiki/w/Darklight",
      "name": "Darklight",
      "breakdownNotes": "",
      "label": "darklight",
      "selected": false
    },
    {
      "image": "https://i.imgur.com/0d9nkK4.png",
      "wikiLink": "https://runescape.wiki/w/Planted_feet_perk",
      "name": "Planted feet perk",
      "breakdownNotes": "Not needed if <img class=\"disc-emoji\" src=\"https://cdn.discordapp.com/emojis/994644352871714836.png?v=1\" /> is owned",
      "label": "pf",
      "selected": false
    },
    {
      "image": "",
      "name": "",
      "breakdownNotes": "",
      "label": "",
      "selected": false
    },
    {
      "image": "",
      "name": "",
      "breakdownNotes": "",
      "label": "",
      "selected": false
    },
    {
      "image": "",
      "name": "",
      "breakdownNotes": "",
      "label": "",
      "selected": false
    },
    {
      "image": "https://i.imgur.com/2uy0pnb.png",
      "wikiLink": "https://runescape.wiki/w/Super_restore_flask#(6)",
      "name": "Super restore flask (6)",
      "breakdownNotes": "",
      "label": "restore",
      "selected": false
    },
    {
      "image": "https://i.imgur.com/2uy0pnb.png",
      "wikiLink": "https://runescape.wiki/w/Super_restore_flask#(6)",
      "name": "Super restore flask (6)",
      "breakdownNotes": "",
      "label": "restore",
      "selected": false
    },
    {
      "image": "https://i.imgur.com/LAVYvrE.png",
      "wikiLink": "https://runescape.wiki/w/Dark_Sliver_of_Leng",
      "name": "Dark Sliver of Leng",
      "breakdownNotes": "Can also be any high-tiered offhand such as <img class=\"disc-emoji\" src=\"https://cdn.discordapp.com/emojis/915232153787334677.png?v=1\" />",
      "label": "lengoh",
      "selected": false
    },
    {
      "image": "",
      "name": "",
      "breakdownNotes": "",
      "label": "",
      "selected": false
    },
    {
      "image": "",
      "name": "",
      "breakdownNotes": "",
      "label": "",
      "selected": false
    },
    {
      "image": "",
      "name": "",
      "breakdownNotes": "",
      "label": "",
      "selected": false
    },
    {
      "image": "https://i.imgur.com/B4vyqxv.png",
      "wikiLink": "https://runescape.wiki/w/Slayer_cape_(t)",
      "name": "Slayer cape (t)",
      "breakdownNotes": "For teleporting to Morvran",
      "label": "slayercape",
      "selected": false
    },
    {
      "image": "https://i.imgur.com/fOJHeIX.png",
      "wikiLink": "https://runescape.wiki/w/Distraction_&_Diversion_reset_token_(weekly)",
      "name": "Distraction & Diversion reset token (weekly)",
      "breakdownNotes": "",
      "label": "weeklytoken",
      "selected": false
    },
    {
      "image": "https://i.imgur.com/30CSA7N.png",
      "wikiLink": "https://runescape.wiki/w/Dominion_mines",
      "name": "Dominion mines",
      "breakdownNotes": "",
      "label": "20mines",
      "selected": false
    },
    {
      "image": "https://i.imgur.com/Mjyhuk5.png",
      "wikiLink": "https://runescape.wiki/w/Obliteration",
      "name": "Obliteration",
      "breakdownNotes": "Staff with Ruthless for 4t",
      "label": "obliteration",
      "selected": false
    },
    {
      "image": "",
      "name": "",
      "breakdownNotes": "",
      "label": "",
      "selected": false
    },
    {
      "image": "",
      "name": "",
      "breakdownNotes": "",
      "label": "",
      "selected": false
    },
    {
      "image": "",
      "name": "",
      "breakdownNotes": "",
      "label": "",
      "selected": false
    },
    {
      "image": "https://i.imgur.com/gDZtYb4.png",
      "wikiLink": "https://runescape.wiki/w/Grasping_rune_pouch_(blue)",
      "name": "Grasping rune pouch (blue)",
      "breakdownNotes": "Chaos | Air | Water | Fire - Runes for <img class=\"disc-emoji\" src=\"https://cdn.discordapp.com/emojis/856635090745950258.png?v=1\" /> <img class=\"disc-emoji\" src=\"https://cdn.discordapp.com/emojis/537340400185245701.png?v=1\" /> <img class=\"disc-emoji\" src=\"https://cdn.discordapp.com/emojis/537338981747261446.png?v=1\" />",
      "label": "graspingpouchblue",
      "selected": false
    }
  ],
  "relics": {
    "primaryRelics": [
      {
        "image": "",
        "name": "",
        "breakdownNotes": "",
        "label": ""
      },
      {
        "image": "",
        "name": "",
        "breakdownNotes": "",
        "label": ""
      },
      {
        "image": "",
        "name": "",
        "breakdownNotes": "",
        "label": ""
      }
    ],
    "alternativeRelics": [
      {
        "image": "",
        "name": "",
        "breakdownNotes": "",
        "label": ""
      },
      {
        "image": "",
        "name": "",
        "breakdownNotes": "",
        "label": ""
      },
      {
        "image": "",
        "name": "",
        "breakdownNotes": "",
        "label": ""
      }
    ]
  },
  "familiars": {
    "alternativeFamiliars": [
      {
        "image": "",
        "name": "",
        "breakdownNotes": "",
        "label": ""
      },
      {
        "image": "",
        "name": "",
        "breakdownNotes": "",
        "label": ""
      },
      {
        "image": "",
        "name": "",
        "breakdownNotes": "",
        "label": ""
      }
    ],
    "primaryFamiliars": [
      {
        "image": "",
        "name": "",
        "breakdownNotes": "",
        "label": ""
      }
    ]
  }
}