{
  "presetName": "Melee NM Twin Furies",
  "presetNotes": "Use <img title=\"eof\" class=\"disc-emoji\" src=\"https://cdn.discordapp.com/emojis/787526151978614824.png?v=1\" /> with <img title=\"dragonclaw\" class=\"disc-emoji\" src=\"https://cdn.discordapp.com/emojis/779048041088024606.png?v=1\" />or <img title=\"dragondagger\" class=\"disc-emoji\" src=\"https://cdn.discordapp.com/emojis/779048040644083733.png?v=1\" /> depending on which rotation you're following.",
  "equipmentSlots": [
    {
      "image": "https://i.imgur.com/EVh5SwD.png",
      "wikiLink": "https://runescape.wiki/w/Vestments_of_havoc_hood",
      "name": "Vestments of havoc hood",
      "breakdownNotes": "",
      "label": "vestmenthood"
    },
    {
      "image": "https://i.imgur.com/bfzX8Up.png",
      "wikiLink": "https://runescape.wiki/w/Igneous_Kal-Ket",
      "name": "Igneous Kal-Ket",
      "breakdownNotes": "",
      "label": "kalket"
    },
    {
      "image": "https://i.imgur.com/JMC7t7Y.png",
      "wikiLink": "https://runescape.wiki/w/Dragon_claws",
      "name": "EoF - Dragon claws",
      "breakdownNotes": "<span>Or dragon dagger </span><img title=\"dragondagger\" class=\"disc-emoji\" src=\"https://cdn.discordapp.com/emojis/779048040644083733.png?v=1\" /><span> if following the second rotation.</span>",
      "label": "eofred"
    },
    {
      "image": "https://i.imgur.com/wFdHN9C.png",
      "wikiLink": "https://runescape.wiki/w/Dark_Shard_of_Leng",
      "name": "Dark Shard of Leng",
      "breakdownNotes": "",
      "label": "lengmh"
    },
    {
      "image": "https://i.imgur.com/E5ptfu6.png",
      "wikiLink": "https://runescape.wiki/w/Vestments_of_havoc_robe_top",
      "name": "Vestments of havoc robe top",
      "breakdownNotes": "",
      "label": "vestmentbody"
    },
    {
      "image": "https://i.imgur.com/LAVYvrE.png",
      "wikiLink": "https://runescape.wiki/w/Dark_Sliver_of_Leng",
      "name": "Dark Sliver of Leng",
      "breakdownNotes": "",
      "label": "lengoh"
    },
    {
      "image": "https://i.imgur.com/mz7GwWF.png",
      "wikiLink": "https://runescape.wiki/w/Vestments_of_havoc_robe_bottom",
      "name": "Vestments of havoc robe bottom",
      "breakdownNotes": "",
      "label": "vestmentlegs"
    },
    {
      "image": "https://i.imgur.com/U4Wa7vb.png",
      "wikiLink": "https://runescape.wiki/w/Gloves_of_passage",
      "name": "Gloves of passage",
      "breakdownNotes": "",
      "label": "glovesofpassage"
    },
    {
      "image": "https://i.imgur.com/FarIA5V.png",
      "wikiLink": "https://runescape.wiki/w/Vestments_of_havoc_boots",
      "name": "Vestments of havoc boots",
      "breakdownNotes": "",
      "label": "vestmentboots"
    },
    {
      "image": "https://i.imgur.com/cnIOClx.png",
      "wikiLink": "https://runescape.wiki/w/Reaver's_ring",
      "name": "Reaver's ring",
      "breakdownNotes": "<br />",
      "label": "reaverring"
    },
    {
      "image": "https://i.imgur.com/Mk7jbjC.png",
      "wikiLink": "https://runescape.wiki/w/Grasping_rune_pouch",
      "name": "Grasping rune pouch",
      "breakdownNotes": "",
      "label": "graspingpouch"
    },
    {
      "image": "https://i.imgur.com/e50R2q0.png",
      "wikiLink": "https://runescape.wiki/w/Berserker_aura",
      "name": "Berserker aura",
      "breakdownNotes": "",
      "label": "zerk"
    },
    {
      "image": "https://i.imgur.com/eAO0PdY.png",
      "wikiLink": "https://runescape.wiki/w/Erethdor's_grimoire",
      "name": "Erethdor's grimoire",
      "breakdownNotes": "Can use <img title=\"scriptureofful\" class=\"disc-emoji\" src=\"https://cdn.discordapp.com/emojis/902209626412560395.png?v=1\" /> instead.",
      "label": "grim"
    }
  ],
  "inventorySlots": [
    {
      "image": "https://i.imgur.com/9GP63eS.png",
      "wikiLink": "https://runescape.wiki/w/Elder_overload_salve#(6)",
      "name": "Elder overload salve (6)",
      "breakdownNotes": "",
      "label": "salve"
    },
    {
      "image": "https://i.imgur.com/9GP63eS.png",
      "wikiLink": "https://runescape.wiki/w/Elder_overload_salve#(6)",
      "name": "Elder overload salve (6)",
      "breakdownNotes": "",
      "label": "salve"
    },
    {
      "image": "https://i.imgur.com/2vI8jNm.png",
      "wikiLink": "https://runescape.wiki/w/Vulnerabilty_bombs",
      "name": "Vulnerabilty bombs",
      "breakdownNotes": "",
      "label": "vuln"
    },
    null,
    null,
    {
      "image": "https://i.imgur.com/5dumsv0.png",
      "wikiLink": "https://runescape.wiki/w/Binding_contract_(kal'gerion_demon)",
      "name": "Binding contract (kal'gerion demon)",
      "breakdownNotes": "",
      "label": "kalg"
    },
    {
      "image": "https://i.imgur.com/hjoH9xr.png",
      "wikiLink": "https://runescape.wiki/w/Kal%27gerion_Demon_scroll_(Crit-i-Kal)",
      "name": "Kal'gerion Demon scroll (Crit-i-Kal)",
      "breakdownNotes": "",
      "label": "kalgscrolls500"
    },
    {
      "image": "https://i.imgur.com/IqAjWRF.png",
      "wikiLink": "https://runescape.wiki/w/Adrenaline_renewal_potion#(4)",
      "name": "Adrenaline renewal potion (4)",
      "breakdownNotes": "",
      "label": "renewal4"
    },
    {
      "image": "https://i.imgur.com/IqAjWRF.png",
      "wikiLink": "https://runescape.wiki/w/Adrenaline_renewal_potion#(4)",
      "name": "Adrenaline renewal potion (4)",
      "breakdownNotes": "",
      "label": "renewal4"
    },
    {
      "image": "https://i.imgur.com/IqAjWRF.png",
      "wikiLink": "https://runescape.wiki/w/Adrenaline_renewal_potion#(4)",
      "name": "Adrenaline renewal potion (4)",
      "breakdownNotes": "",
      "label": "renewal4"
    },
    {
      "image": "https://i.imgur.com/IqAjWRF.png",
      "wikiLink": "https://runescape.wiki/w/Adrenaline_renewal_potion#(4)",
      "name": "Adrenaline renewal potion (4)",
      "breakdownNotes": "",
      "label": "renewal4"
    },
    null,
    null,
    null,
    {
      "image": "https://i.imgur.com/IqAjWRF.png",
      "wikiLink": "https://runescape.wiki/w/Adrenaline_renewal_potion#(4)",
      "name": "Adrenaline renewal potion (4)",
      "breakdownNotes": "",
      "label": "renewal4"
    },
    {
      "image": "https://i.imgur.com/IqAjWRF.png",
      "wikiLink": "https://runescape.wiki/w/Adrenaline_renewal_potion#(4)",
      "name": "Adrenaline renewal potion (4)",
      "breakdownNotes": "",
      "label": "renewal4"
    },
    {
      "image": "https://i.imgur.com/IqAjWRF.png",
      "wikiLink": "https://runescape.wiki/w/Adrenaline_renewal_potion#(4)",
      "name": "Adrenaline renewal potion (4)",
      "breakdownNotes": "",
      "label": "renewal4"
    },
    {
      "image": "https://i.imgur.com/IqAjWRF.png",
      "wikiLink": "https://runescape.wiki/w/Adrenaline_renewal_potion#(4)",
      "name": "Adrenaline renewal potion (4)",
      "breakdownNotes": "",
      "label": "renewal4"
    },
    null,
    null,
    null,
    {
      "image": "https://i.imgur.com/IqAjWRF.png",
      "wikiLink": "https://runescape.wiki/w/Adrenaline_renewal_potion#(4)",
      "name": "Adrenaline renewal potion (4)",
      "breakdownNotes": "",
      "label": "renewal4"
    },
    {
      "image": "https://i.imgur.com/IqAjWRF.png",
      "wikiLink": "https://runescape.wiki/w/Adrenaline_renewal_potion#(4)",
      "name": "Adrenaline renewal potion (4)",
      "breakdownNotes": "",
      "label": "renewal4"
    },
    {
      "image": "https://i.imgur.com/IqAjWRF.png",
      "wikiLink": "https://runescape.wiki/w/Adrenaline_renewal_potion#(4)",
      "name": "Adrenaline renewal potion (4)",
      "breakdownNotes": "",
      "label": "renewal4"
    },
    {
      "image": "https://i.imgur.com/IqAjWRF.png",
      "wikiLink": "https://runescape.wiki/w/Adrenaline_renewal_potion#(4)",
      "name": "Adrenaline renewal potion (4)",
      "breakdownNotes": "",
      "label": "renewal4"
    },
    null,
    null,
    null
  ],
  "relics": {
    "primaryRelics": [
      {
        "image": "https://i.imgur.com/Gfdc9u6.png",
        "name": "Conservation of Energy",
        "breakdownNotes": "",
        "description": "After using an ultimate ability, you will regain 10% adrenaline.",
        "label": "conservationofenergy",
        "energy": 350
      },
      {
        "image": "https://i.imgur.com/W87TO3O.png",
        "name": "Fury of the Small",
        "breakdownNotes": "",
        "description": "All adrenaline generating basic abilities generate +1% adrenaline.",
        "label": "furyofthesmall",
        "energy": 150
      },
      {
        "image": "",
        "name": "",
        "breakdownNotes": "",
        "label": ""
      }
    ],
    "alternativeRelics": [
      {
        "image": "",
        "name": "",
        "breakdownNotes": "",
        "label": ""
      },
      {
        "image": "",
        "name": "",
        "breakdownNotes": "",
        "label": ""
      },
      {
        "image": "",
        "name": "",
        "breakdownNotes": "",
        "label": ""
      }
    ]
  },
  "familiars": {
    "alternativeFamiliars": [
      {
        "image": "",
        "name": "",
        "breakdownNotes": "",
        "label": ""
      },
      {
        "image": "",
        "name": "",
        "breakdownNotes": "",
        "label": ""
      },
      {
        "image": "",
        "name": "",
        "breakdownNotes": "",
        "label": ""
      }
    ],
    "primaryFamiliars": [
      {
        "image": "https://i.imgur.com/4oLwaZJ.png",
        "name": "Kal'gerion Demon",
        "breakdownNotes": "",
        "label": "kalgdemon"
      }
    ]
  }
}