{
  "presetName": "zammy main mage",
  "presetNotes": "",
  "equipmentSlots": [
    {
      "image": "https://i.imgur.com/jxHhKUO.png",
      "wikiLink": "https://runescape.wiki/w/Anima_core_helm_of_sliske",
      "name": "Anima core helm of sliske",
      "breakdownNotes": "",
      "label": "sliskehelm"
    },
    {
      "image": "https://i.imgur.com/v4dRHBk.png",
      "wikiLink": "https://runescape.wiki/w/Igneous_Kal-Mej",
      "name": "Igneous Kal-Mej",
      "breakdownNotes": "",
      "label": "kalmej"
    },
    {
      "image": "https://i.imgur.com/nu7QSbh.png",
      "wikiLink": "https://runescape.wiki/w/Guthix_staff",
      "name": "EoF - Guthix staff",
      "breakdownNotes": "",
      "label": "eofpurple"
    },
    {
      "image": "https://i.imgur.com/AI12yBk.png",
      "wikiLink": "https://runescape.wiki/w/Fractured_Staff_of_Armadyl",
      "name": "Fractured Staff of Armadyl",
      "breakdownNotes": "",
      "label": "fsoa"
    },
    {
      "image": "https://i.imgur.com/FMvke44.png",
      "wikiLink": "https://runescape.wiki/w/Anima_core_body_of_sliske",
      "name": "Anima core body of sliske",
      "breakdownNotes": "",
      "label": "sliskebody"
    },
    null,
    {
      "image": "https://i.imgur.com/0HQcba9.png",
      "wikiLink": "https://runescape.wiki/w/Anima_core_legs_of_sliske",
      "name": "Anima core legs of sliske",
      "breakdownNotes": "",
      "label": "sliskelegs"
    },
    {
      "image": "https://i.imgur.com/ia3JNEm.png",
      "wikiLink": "https://runescape.wiki/w/Deathtouched_bracelet",
      "name": "Deathtouched bracelet",
      "breakdownNotes": "",
      "label": "dtb"
    },
    {
      "image": "https://i.imgur.com/2VPk1SN.png",
      "wikiLink": "https://runescape.wiki/w/Blast_diffusion_boots",
      "name": "Blast diffusion boots",
      "breakdownNotes": "",
      "label": "diffusion"
    },
    {
      "image": "https://i.imgur.com/Zs7j4JG.png",
      "wikiLink": "https://runescape.wiki/w/Channeller's_ring",
      "name": "Channeller's ring",
      "breakdownNotes": "",
      "label": "channellerring"
    },
    {
      "image": "https://i.imgur.com/3pFXvMR.png",
      "wikiLink": "https://runescape.wiki/w/Zemouregal%27s_nexus",
      "name": "Zemoregal's Nexus",
      "breakdownNotes": "",
      "label": "zemouregalsnexus"
    },
    {
      "image": "https://i.imgur.com/br11PCq.png",
      "wikiLink": "https://runescape.wiki/w/Mahjarrat_aura",
      "name": "Mahjarrat aura",
      "breakdownNotes": "",
      "label": "mahj"
    },
    {
      "image": "https://i.imgur.com/eAO0PdY.png",
      "wikiLink": "https://runescape.wiki/w/Erethdor's_grimoire",
      "name": "Erethdor's grimoire",
      "breakdownNotes": "",
      "label": "grim"
    }
  ],
  "inventorySlots": [
    {
      "image": "https://i.imgur.com/9GP63eS.png",
      "wikiLink": "https://runescape.wiki/w/Elder_overload_salve#(6)",
      "name": "Elder overload salve (6)",
      "breakdownNotes": "",
      "label": "salve",
      "selected": false
    },
    {
      "image": "https://i.imgur.com/IqAjWRF.png",
      "wikiLink": "https://runescape.wiki/w/Adrenaline_renewal_potion#(4)",
      "name": "Adrenaline renewal potion (4)",
      "breakdownNotes": "",
      "label": "renewal4",
      "selected": false
    },
    {
      "image": "https://i.imgur.com/2uy0pnb.png",
      "wikiLink": "https://runescape.wiki/w/Super_restore_flask#(6)",
      "name": "Super restore flask (6)",
      "breakdownNotes": "",
      "label": "restore",
      "selected": false
    },
    {
      "image": "https://i.imgur.com/2uy0pnb.png",
      "wikiLink": "https://runescape.wiki/w/Super_restore_flask#(6)",
      "name": "Super restore flask (6)",
      "breakdownNotes": "",
      "label": "restore",
      "selected": false
    },
    {
      "image": "https://i.imgur.com/2vI8jNm.png",
      "wikiLink": "https://runescape.wiki/w/Vulnerabilty_bombs",
      "name": "Vulnerabilty bombs",
      "breakdownNotes": "",
      "label": "vuln",
      "selected": false
    },
    {
      "image": "https://i.imgur.com/n9C7iSA.png",
      "wikiLink": "https://runescape.wiki/w/Powerburst_of_vitality#(4)",
      "name": "Powerburst of vitality (4)",
      "breakdownNotes": "",
      "label": "vitality4",
      "selected": false
    },
    {
      "image": "https://i.imgur.com/nC5xTAR.png",
      "wikiLink": "https://runescape.wiki/w/Enhanced_excalibur",
      "name": "Enhanced excalibur",
      "breakdownNotes": "",
      "label": "excal",
      "selected": false
    },
    {
      "image": "https://i.imgur.com/NTlFcpC.png",
      "wikiLink": "https://runescape.wiki/w/Saradomin_brew_flask#(6)",
      "name": "Saradomin brew flask (6)",
      "breakdownNotes": "",
      "label": "sara",
      "selected": false
    },
    {
      "image": "https://i.imgur.com/NTlFcpC.png",
      "wikiLink": "https://runescape.wiki/w/Saradomin_brew_flask#(6)",
      "name": "Saradomin brew flask (6)",
      "breakdownNotes": "",
      "label": "sara",
      "selected": false
    },
    {
      "image": "https://i.imgur.com/NTlFcpC.png",
      "wikiLink": "https://runescape.wiki/w/Saradomin_brew_flask#(6)",
      "name": "Saradomin brew flask (6)",
      "breakdownNotes": "",
      "label": "sara",
      "selected": false
    },
    {
      "image": "https://i.imgur.com/NTlFcpC.png",
      "wikiLink": "https://runescape.wiki/w/Saradomin_brew_flask#(6)",
      "name": "Saradomin brew flask (6)",
      "breakdownNotes": "",
      "label": "sara",
      "selected": false
    },
    {
      "image": "https://i.imgur.com/bYjvXqa.png",
      "wikiLink": "https://runescape.wiki/w/Seismic_wand",
      "name": "Seismic wand",
      "breakdownNotes": "",
      "label": "swand",
      "selected": false
    },
    {
      "image": "https://i.imgur.com/9Z9ChMg.png",
      "wikiLink": "https://runescape.wiki/w/Seismic_singularity",
      "name": "Seismic singularity",
      "breakdownNotes": "",
      "label": "sing",
      "selected": false
    },
    {
      "image": "https://i.imgur.com/yh8LZY1.png",
      "wikiLink": "https://runescape.wiki/w/Large_rune_pouch_(blue)",
      "name": "Large rune pouch (blue)",
      "breakdownNotes": "Blood | Astral | Body",
      "label": "pouchblue",
      "selected": false
    },
    {
      "image": "https://i.imgur.com/RD2LyxF.png",
      "wikiLink": "https://runescape.wiki/w/Blue_blubber_jellyfish",
      "name": "Blue blubber jellyfish",
      "breakdownNotes": "",
      "label": "jelly",
      "selected": false
    },
    {
      "image": "https://i.imgur.com/RD2LyxF.png",
      "wikiLink": "https://runescape.wiki/w/Blue_blubber_jellyfish",
      "name": "Blue blubber jellyfish",
      "breakdownNotes": "",
      "label": "jelly",
      "selected": false
    },
    {
      "image": "https://i.imgur.com/RD2LyxF.png",
      "wikiLink": "https://runescape.wiki/w/Blue_blubber_jellyfish",
      "name": "Blue blubber jellyfish",
      "breakdownNotes": "",
      "label": "jelly",
      "selected": false
    },
    {
      "image": "https://i.imgur.com/RD2LyxF.png",
      "wikiLink": "https://runescape.wiki/w/Blue_blubber_jellyfish",
      "name": "Blue blubber jellyfish",
      "breakdownNotes": "",
      "label": "jelly",
      "selected": false
    },
    {
      "image": "https://i.imgur.com/qocLc4k.png",
      "wikiLink": "https://runescape.wiki/w/Sailfish",
      "name": "Sailfish",
      "breakdownNotes": "",
      "label": "sailfish",
      "selected": false
    },
    {
      "image": "https://i.imgur.com/y5vAY4M.png",
      "wikiLink": "https://runescape.wiki/w/Ring_of_death",
      "name": "Ring of death",
      "breakdownNotes": "",
      "label": "rod",
      "selected": false
    },
    {
      "image": "https://i.imgur.com/yrnlR2T.png",
      "wikiLink": "https://runescape.wiki/w/Grasping_rune_pouch_(pink)",
      "name": "Grasping rune pouch (pink)",
      "breakdownNotes": "Death | Earth | Law | Cosmic",
      "label": "graspingpouchpink",
      "selected": false
    },
    {
      "image": "https://i.imgur.com/RD2LyxF.png",
      "wikiLink": "https://runescape.wiki/w/Blue_blubber_jellyfish",
      "name": "Blue blubber jellyfish",
      "breakdownNotes": "",
      "label": "jelly",
      "selected": false
    },
    {
      "image": "https://i.imgur.com/RD2LyxF.png",
      "wikiLink": "https://runescape.wiki/w/Blue_blubber_jellyfish",
      "name": "Blue blubber jellyfish",
      "breakdownNotes": "",
      "label": "jelly",
      "selected": false
    },
    {
      "image": "https://i.imgur.com/RD2LyxF.png",
      "wikiLink": "https://runescape.wiki/w/Blue_blubber_jellyfish",
      "name": "Blue blubber jellyfish",
      "breakdownNotes": "",
      "label": "jelly",
      "selected": false
    },
    {
      "image": "https://i.imgur.com/RD2LyxF.png",
      "wikiLink": "https://runescape.wiki/w/Blue_blubber_jellyfish",
      "name": "Blue blubber jellyfish",
      "breakdownNotes": "",
      "label": "jelly",
      "selected": false
    },
    {
      "image": "https://i.imgur.com/qocLc4k.png",
      "wikiLink": "https://runescape.wiki/w/Sailfish",
      "name": "Sailfish",
      "breakdownNotes": "",
      "label": "sailfish",
      "selected": false
    },
    {
      "image": "https://i.imgur.com/qocLc4k.png",
      "wikiLink": "https://runescape.wiki/w/Sailfish",
      "name": "Sailfish",
      "breakdownNotes": "",
      "label": "sailfish",
      "selected": false
    },
    {
      "image": "https://i.imgur.com/hvhOeDs.png",
      "wikiLink": "https://runescape.wiki/w/Grasping_rune_pouch_(black)",
      "name": "Grasping rune pouch (black)",
      "breakdownNotes": "Blood | Astral | Body | Soul",
      "label": "graspingpouchblack",
      "selected": false
    }
  ],
  "relics": {
    "primaryRelics": [
      {
        "image": "https://i.imgur.com/Gfdc9u6.png",
        "name": "Conservation of Energy",
        "breakdownNotes": "",
        "description": "After using an ultimate ability, you will regain 10% adrenaline.",
        "label": "conservationofenergy",
        "energy": 350
      },
      {
        "image": "https://i.imgur.com/xXWYCHG.png",
        "name": "Berserkers Fury",
        "breakdownNotes": "",
        "description": "Deal up to +5.5% damage (all styles) the lower your current life points are below max. (Doesn't stack with Dharok's set effect.)",
        "label": "berserkersfury",
        "energy": 250
      },
      {
        "image": "https://i.imgur.com/7e6Juey.png",
        "name": "Font of Life",
        "breakdownNotes": "",
        "description": "Increases maximum health by 500.",
        "label": "fontoflife",
        "energy": 50
      }
    ],
    "alternativeRelics": [
      {
        "image": "",
        "name": "",
        "breakdownNotes": "",
        "label": ""
      },
      {
        "image": "",
        "name": "",
        "breakdownNotes": "",
        "label": ""
      },
      {
        "image": "",
        "name": "",
        "breakdownNotes": "",
        "label": ""
      }
    ]
  },
  "familiars": {
    "alternativeFamiliars": [
      {
        "image": "",
        "name": "",
        "breakdownNotes": "",
        "label": ""
      },
      {
        "image": "",
        "name": "",
        "breakdownNotes": "",
        "label": ""
      },
      {
        "image": "",
        "name": "",
        "breakdownNotes": "",
        "label": ""
      }
    ],
    "primaryFamiliars": [
      {
        "image": "https://i.imgur.com/4oLwaZJ.png",
        "name": "Kal'gerion Demon",
        "breakdownNotes": "",
        "label": "kalgdemon"
      }
    ]
  }
}