{
  "presetName": "Hybrid Rathis/Ori",
  "presetNotes": "<span>Cast prism occasionally to heal your reaver</span>",
  "equipmentSlots": [
    {
      "image": "https://i.imgur.com/iPtkkKN.png",
      "wikiLink": "https://runescape.wiki/w/Elite_tectonic_mask",
      "name": "Elite tectonic mask",
      "breakdownNotes": "",
      "label": "etectohelm"
    },
    {
      "image": "https://i.imgur.com/jcfkzGn.png",
      "wikiLink": "https://runescape.wiki/w/Igneous_Kal-Zuk",
      "name": "Igneous Kal-Zuk",
      "breakdownNotes": "",
      "label": "kalzuk"
    },
    {
      "image": "https://i.imgur.com/tsyhx6q.png",
      "wikiLink": "https://runescape.wiki/w/Necklace_of_Salamancy",
      "name": "Necklace of Salamancy",
      "breakdownNotes": "Check accuracies if not unowned and not on task",
      "label": "salamancy"
    },
    {
      "image": "https://i.imgur.com/kyKIKBC.png",
      "wikiLink": "https://runescape.wiki/w/Wand_of_the_praesul",
      "name": "Wand of the praesul",
      "breakdownNotes": "",
      "label": "pwand"
    },
    {
      "image": "https://i.imgur.com/NftWcLQ.png",
      "wikiLink": "https://runescape.wiki/w/Elite_tectonic_robe_top",
      "name": "Elite tectonic robe top",
      "breakdownNotes": "",
      "label": "etectotop"
    },
    {
      "image": "https://i.imgur.com/rvFepeU.png",
      "wikiLink": "https://runescape.wiki/w/Imperium_core",
      "name": "Imperium core",
      "breakdownNotes": "",
      "label": "core"
    },
    {
      "image": "https://i.imgur.com/0TXtWf2.png",
      "wikiLink": "https://runescape.wiki/w/Elite_tectonic_robe_bottom",
      "name": "Elite tectonic robe bottom",
      "breakdownNotes": "",
      "label": "etectolegs"
    },
    {
      "image": "https://i.imgur.com/LutTgCH.png",
      "wikiLink": "https://runescape.wiki/w/Cinderbane_gloves",
      "name": "Cinderbane gloves",
      "breakdownNotes": "",
      "label": "cinder"
    },
    {
      "image": "https://i.imgur.com/KUGqEdN.png",
      "wikiLink": "https://runescape.wiki/w/Enhanced_blast_diffusion_boots",
      "name": "Enhanced blast diffusion boots",
      "breakdownNotes": "",
      "label": "enhancedblastdiff"
    },
    {
      "image": "https://i.imgur.com/cnIOClx.png",
      "wikiLink": "https://runescape.wiki/w/Reaver's_ring",
      "name": "Reaver's ring",
      "breakdownNotes": "",
      "label": "reaverring"
    },
    {
      "image": "https://i.imgur.com/gDZtYb4.png",
      "wikiLink": "https://runescape.wiki/w/Grasping_rune_pouch_(blue)",
      "name": "Grasping rune pouch (blue)",
      "breakdownNotes": "<span>Chaos | Air | Water | Fire - Runes for Smoke Cloud, Incite Fear, Exsanguinate, Spellbook swap (Standard), Entangle, Spellbook swap (Lunar), Vengeance, and Disruption shield</span>",
      "label": "graspingpouchblue"
    },
    {
      "image": "https://i.imgur.com/5fIllNu.png",
      "wikiLink": "https://runescape.wiki/w/Maniacal_aura",
      "name": "Maniacal aura",
      "breakdownNotes": "Needed to not splash entangle unless on task",
      "label": "mani"
    },
    {
      "image": "https://i.imgur.com/lPppoD4.png",
      "wikiLink": "https://runescape.wiki/w/Scripture_of_Ful",
      "name": "Scripture of Ful",
      "breakdownNotes": "Grimoire would be slightly better but much higher cost",
      "label": "scriptureofful"
    }
  ],
  "inventorySlots": [
    {
      "image": "https://i.imgur.com/11pg3gM.png",
      "wikiLink": "https://runescape.wiki/w/Jaws_of_the_Abyss",
      "name": "Jaws of the Abyss",
      "breakdownNotes": "",
      "label": "jawsoftheabyss"
    },
    {
      "image": "https://i.imgur.com/9GP63eS.png",
      "wikiLink": "https://runescape.wiki/w/Elder_overload_salve#(6)",
      "name": "Elder overload salve (6)",
      "breakdownNotes": "",
      "label": "salve"
    },
    {
      "image": "https://i.imgur.com/9GP63eS.png",
      "wikiLink": "https://runescape.wiki/w/Elder_overload_salve#(6)",
      "name": "Elder overload salve (6)",
      "breakdownNotes": "",
      "label": "salve"
    },
    {
      "image": "https://i.imgur.com/KyZkJoc.png",
      "wikiLink": "https://runescape.wiki/w/Weapon_poison+++_flask#(6)",
      "name": "Weapon poison+++ flask (6)",
      "breakdownNotes": "",
      "label": "poison6"
    },
    {
      "image": "https://i.imgur.com/Swtl8pP.png",
      "wikiLink": "https://runescape.wiki/w/Adrenaline_renewal_flask#(6)",
      "name": "Adrenaline renewal flask (6)",
      "breakdownNotes": "",
      "label": "renewal6"
    },
    {
      "image": "https://i.imgur.com/yrnlR2T.png",
      "wikiLink": "https://runescape.wiki/w/Grasping_rune_pouch_(pink)",
      "name": "Grasping rune pouch (pink)",
      "breakdownNotes": "Death | Earth | Law | Cosmic <span>- Runes for Smoke Cloud, Incite Fear, Exsanguinate, Spellbook swap (Standard), Entangle, Spellbook swap (Lunar), Vengeance, and Disruption shield</span>",
      "label": "graspingpouchpink"
    },
    {
      "image": "https://i.imgur.com/hvhOeDs.png",
      "wikiLink": "https://runescape.wiki/w/Grasping_rune_pouch_(black)",
      "name": "Grasping rune pouch (black)",
      "breakdownNotes": "Blood | Astral | Body | Soul <span>- Runes for Smoke Cloud, Incite Fear, Exsanguinate, Spellbook swap (Standard), Entangle, Spellbook swap (Lunar), Vengeance, and Disruption shield</span>",
      "label": "graspingpouchblack"
    },
    {
      "image": "https://i.imgur.com/E5ptfu6.png",
      "wikiLink": "https://runescape.wiki/w/Vestments_of_havoc_robe_top",
      "name": "Vestments of havoc robe top",
      "breakdownNotes": "",
      "label": "vestmentbody"
    },
    {
      "image": "https://i.imgur.com/2vI8jNm.png",
      "wikiLink": "https://runescape.wiki/w/Vulnerabilty_bombs",
      "name": "Vulnerabilty bombs",
      "breakdownNotes": "",
      "label": "vuln"
    },
    {
      "image": "https://i.imgur.com/FVmxMkH.png",
      "wikiLink": "https://runescape.wiki/w/Blessed_flask",
      "name": "Blessed flask",
      "breakdownNotes": "Substitute for 4 restore flasks, 3 of which go into the blessed flask, Kwuarm incense sticks, nihil and inventory slots.",
      "label": "blessed"
    },
    {
      "image": "https://i.imgur.com/Swtl8pP.png",
      "wikiLink": "https://runescape.wiki/w/Adrenaline_renewal_flask#(6)",
      "name": "Adrenaline renewal flask (6)",
      "breakdownNotes": "",
      "label": "renewal6"
    },
    {
      "image": "https://i.imgur.com/Swtl8pP.png",
      "wikiLink": "https://runescape.wiki/w/Adrenaline_renewal_flask#(6)",
      "name": "Adrenaline renewal flask (6)",
      "breakdownNotes": "",
      "label": "renewal6"
    },
    {
      "image": "https://i.imgur.com/Ba7yju8.png",
      "wikiLink": "https://runescape.wiki/w/Kwuarm_incense_sticks",
      "name": "Kwuarm incense sticks",
      "breakdownNotes": "",
      "label": "kwuarmsticks"
    },
    {
      "image": "https://i.imgur.com/3uR1o36.png",
      "wikiLink": "https://runescape.wiki/w/Nature_rune",
      "name": "Nature rune",
      "breakdownNotes": "",
      "label": "naturerune1k"
    },
    {
      "image": "https://i.imgur.com/mz7GwWF.png",
      "wikiLink": "https://runescape.wiki/w/Vestments_of_havoc_robe_bottom",
      "name": "Vestments of havoc robe bottom",
      "breakdownNotes": "",
      "label": "vestmentlegs"
    },
    {
      "image": "https://i.imgur.com/AI12yBk.png",
      "wikiLink": "https://runescape.wiki/w/Fractured_Staff_of_Armadyl",
      "name": "Fractured Staff of Armadyl",
      "breakdownNotes": "",
      "label": "fsoa"
    },
    {
      "image": "https://i.imgur.com/wFdHN9C.png",
      "wikiLink": "https://runescape.wiki/w/Dark_Shard_of_Leng",
      "name": "Dark Shard of Leng",
      "breakdownNotes": "",
      "label": "lengmh"
    },
    {
      "image": "https://i.imgur.com/Swtl8pP.png",
      "wikiLink": "https://runescape.wiki/w/Adrenaline_renewal_flask#(6)",
      "name": "Adrenaline renewal flask (6)",
      "breakdownNotes": "",
      "label": "renewal6"
    },
    {
      "image": "https://i.imgur.com/Swtl8pP.png",
      "wikiLink": "https://runescape.wiki/w/Adrenaline_renewal_flask#(6)",
      "name": "Adrenaline renewal flask (6)",
      "breakdownNotes": "",
      "label": "renewal6"
    },
    {
      "image": "https://i.imgur.com/pSNIBhe.png",
      "wikiLink": "https://runescape.wiki/w/Blood_nihil_pouch",
      "name": "Blood nihil pouch",
      "breakdownNotes": "",
      "label": "bloodnihil"
    },
    {
      "image": "https://i.imgur.com/pjHPdhj.png",
      "wikiLink": "https://runescape.wiki/w/Spring_cleaner_9001",
      "name": "Spring cleaner 9001",
      "breakdownNotes": "",
      "label": "springcleaner"
    },
    {
      "image": "https://i.imgur.com/FarIA5V.png",
      "wikiLink": "https://runescape.wiki/w/Vestments_of_havoc_boots",
      "name": "Vestments of havoc boots",
      "breakdownNotes": "",
      "label": "vestmentboots"
    },
    {
      "image": "https://i.imgur.com/Moh9yya.png",
      "wikiLink": "https://runescape.wiki/w/Abyssal_scourge",
      "name": "Abyssal scourge",
      "breakdownNotes": "",
      "label": "abyssalscourge"
    },
    {
      "image": "https://i.imgur.com/LAVYvrE.png",
      "wikiLink": "https://runescape.wiki/w/Dark_Sliver_of_Leng",
      "name": "Dark Sliver of Leng",
      "breakdownNotes": "",
      "label": "lengoh"
    },
    {
      "image": "https://i.imgur.com/uLkJkio.png",
      "wikiLink": "https://runescape.wiki/w/Masterwork_spear_of_annihilation",
      "name": "Masterwork spear of annihilation",
      "breakdownNotes": "",
      "label": "spear"
    },
    {
      "image": "https://i.imgur.com/nC5xTAR.png",
      "wikiLink": "https://runescape.wiki/w/Enhanced_excalibur",
      "name": "Enhanced excalibur",
      "breakdownNotes": "",
      "label": "excal"
    },
    {
      "image": "https://i.imgur.com/cc9GxHt.png",
      "wikiLink": "https://runescape.wiki/w/Champion's_ring",
      "name": "Champion's ring",
      "breakdownNotes": "Preferably enchanted",
      "label": "championring"
    },
    null
  ],
  "relics": {
    "primaryRelics": [
      {
        "image": "https://i.imgur.com/Gfdc9u6.png",
        "name": "Conservation of Energy",
        "breakdownNotes": "",
        "label": "conservationofenergy",
        "energy": 350
      },
      {
        "image": "https://i.imgur.com/cFlJmWP.png",
        "name": "Death Ward",
        "breakdownNotes": "",
        "label": "deathward",
        "energy": 150
      },
      {
        "image": "https://i.imgur.com/W87TO3O.png",
        "name": "Fury of the Small",
        "breakdownNotes": "",
        "label": "furyofthesmall",
        "energy": 150
      }
    ],
    "alternativeRelics": [
      {
        "image": "https://i.imgur.com/xXWYCHG.png",
        "name": "Berserkers Fury",
        "breakdownNotes": "",
        "label": "berserkersfury",
        "energy": 250
      },
      {
        "image": "https://i.imgur.com/7e6Juey.png",
        "name": "Font of Life",
        "breakdownNotes": "",
        "label": "fontoflife",
        "energy": 50
      },
      {
        "image": "",
        "name": "",
        "breakdownNotes": "",
        "label": ""
      }
    ]
  },
  "familiars": {
    "alternativeFamiliars": [
      {
        "image": "https://i.imgur.com/sxnDQng.png",
        "name": "Blood Reaver",
        "breakdownNotes": "",
        "label": "bloodreaver"
      },
      {
        "image": "",
        "name": "",
        "breakdownNotes": "",
        "label": ""
      },
      {
        "image": "",
        "name": "",
        "breakdownNotes": "",
        "label": ""
      }
    ],
    "primaryFamiliars": [
      {
        "image": "https://i.imgur.com/a2CITlX.png",
        "name": "Blood Nihil",
        "breakdownNotes": "",
        "label": "bloodnihil"
      }
    ]
  }
}